{"external_urls": {"spotify": "https://open.spotify.com/artist/3egWSWp7Y4FyCKIyvXbw7L"}, "followers": {"href": null, "total": 3228156}, "genres": ["italian hip hop", "italian pop", "milan indie"], "href": "https://api.spotify.com/v1/artists/3egWSWp7Y4FyCKIyvXbw7L", "id": "3egWSWp7Y4FyCKIyvXbw7L", "images": [{"url": "https://i.scdn.co/image/ab6761610000e5eb98d994da18bd2edd2c72a107", "height": 640, "width": 640}, {"url": "https://i.scdn.co/image/ab6761610000517498d994da18bd2edd2c72a107", "height": 320, "width": 320}, {"url": "https://i.scdn.co/image/ab6761610000f17898d994da18bd2edd2c72a107", "height": 160, "width": 160}], "name": "Ghali", "popularity": 70, "type": "artist", "uri": "spotify:artist:3egWSWp7Y4FyCKIyvXbw7L"}