{"external_urls": {"spotify": "https://open.spotify.com/artist/5cEE1pTgDhFe8QuigmqxJF"}, "followers": {"href": null, "total": 1364978}, "genres": ["himachali pop", "modern bhajan"], "href": "https://api.spotify.com/v1/artists/5cEE1pTgDhFe8QuigmqxJF", "id": "5cEE1pTgDhFe8QuigmqxJF", "images": [{"url": "https://i.scdn.co/image/ab6761610000e5eb2feffce3170e287e2c143dc7", "height": 640, "width": 640}, {"url": "https://i.scdn.co/image/ab676161000051742feffce3170e287e2c143dc7", "height": 320, "width": 320}, {"url": "https://i.scdn.co/image/ab6761610000f1782feffce3170e287e2c143dc7", "height": 160, "width": 160}], "name": "Hansraj Raghuwanshi", "popularity": 65, "type": "artist", "uri": "spotify:artist:5cEE1pTgDhFe8QuigmqxJF"}