{"album": {"album_type": "album", "artists": [{"external_urls": {"spotify": "https://open.spotify.com/artist/6zqr73J6gm3Son1vnWkbfK"}, "href": "https://api.spotify.com/v1/artists/6zqr73J6gm3Son1vnWkbfK", "id": "6zqr73J6gm3Son1vnWkbfK", "name": "Kis\u00e9", "type": "artist", "uri": "spotify:artist:6zqr73J6gm3Son1vnWkbfK"}], "available_markets": ["AR", "AU", "AT", "BE", "BO", "BR", "BG", "CA", "CL", "CO", "CR", "CY", "CZ", "DK", "DO", "DE", "EC", "EE", "SV", "FI", "FR", "GR", "GT", "HN", "HK", "HU", "IS", "IE", "IT", "LV", "LT", "LU", "MY", "MT", "MX", "NL", "NZ", "NI", "NO", "PA", "PY", "PE", "PH", "PL", "PT", "SG", "SK", "ES", "SE", "CH", "TW", "TR", "UY", "US", "GB", "AD", "LI", "MC", "ID", "JP", "TH", "VN", "RO", "IL", "ZA", "SA", "AE", "BH", "QA", "OM", "KW", "EG", "MA", "DZ", "TN", "LB", "JO", "PS", "IN", "BY", "KZ", "MD", "UA", "AL", "BA", "HR", "ME", "MK", "RS", "SI", "KR", "BD", "PK", "LK", "GH", "KE", "NG", "TZ", "UG", "AG", "AM", "BS", "BB", "BZ", "BT", "BW", "BF", "CV", "CW", "DM", "FJ", "GM", "GE", "GD", "GW", "GY", "HT", "JM", "KI", "LS", "LR", "MW", "MV", "ML", "MH", "FM", "NA", "NR", "NE", "PW", "PG", "PR", "WS", "SM", "ST", "SN", "SC", "SL", "SB", "KN", "LC", "VC", "SR", "TL", "TO", "TT", "TV", "VU", "AZ", "BN", "BI", "KH", "CM", "TD", "KM", "GQ", "SZ", "GA", "GN", "KG", "LA", "MO", "MR", "MN", "NP", "RW", "TG", "UZ", "ZW", "BJ", "MG", "MU", "MZ", "AO", "CI", "DJ", "ZM", "CD", "CG", "IQ", "LY", "TJ", "VE", "ET", "XK"], "external_urls": {"spotify": "https://open.spotify.com/album/5UQxk9LslRTr4Y0QMoIEh8"}, "href": "https://api.spotify.com/v1/albums/5UQxk9LslRTr4Y0QMoIEh8", "id": "5UQxk9LslRTr4Y0QMoIEh8", "images": [{"url": "https://i.scdn.co/image/ab67616d0000b2730ee6027fd7c1ca8865384328", "width": 640, "height": 640}, {"url": "https://i.scdn.co/image/ab67616d00001e020ee6027fd7c1ca8865384328", "width": 300, "height": 300}, {"url": "https://i.scdn.co/image/ab67616d000048510ee6027fd7c1ca8865384328", "width": 64, "height": 64}], "name": "BandoBabySeason", "release_date": "2024-02-23", "release_date_precision": "day", "total_tracks": 13, "type": "album", "uri": "spotify:album:5UQxk9LslRTr4Y0QMoIEh8"}, "artists": [{"external_urls": {"spotify": "https://open.spotify.com/artist/6zqr73J6gm3Son1vnWkbfK"}, "href": "https://api.spotify.com/v1/artists/6zqr73J6gm3Son1vnWkbfK", "id": "6zqr73J6gm3Son1vnWkbfK", "name": "Kis\u00e9", "type": "artist", "uri": "spotify:artist:6zqr73J6gm3Son1vnWkbfK"}, {"external_urls": {"spotify": "https://open.spotify.com/artist/1O4dvMoyQSIClCii6DSai8"}, "href": "https://api.spotify.com/v1/artists/1O4dvMoyQSIClCii6DSai8", "id": "1O4dvMoyQSIClCii6DSai8", "name": "Manuel", "type": "artist", "uri": "spotify:artist:1O4dvMoyQSIClCii6DSai8"}], "available_markets": ["AR", "AU", "AT", "BE", "BO", "BR", "BG", "CA", "CL", "CO", "CR", "CY", "CZ", "DK", "DO", "DE", "EC", "EE", "SV", "FI", "FR", "GR", "GT", "HN", "HK", "HU", "IS", "IE", "IT", "LV", "LT", "LU", "MY", "MT", "MX", "NL", "NZ", "NI", "NO", "PA", "PY", "PE", "PH", "PL", "PT", "SG", "SK", "ES", "SE", "CH", "TW", "TR", "UY", "US", "GB", "AD", "LI", "MC", "ID", "JP", "TH", "VN", "RO", "IL", "ZA", "SA", "AE", "BH", "QA", "OM", "KW", "EG", "MA", "DZ", "TN", "LB", "JO", "PS", "IN", "BY", "KZ", "MD", "UA", "AL", "BA", "HR", "ME", "MK", "RS", "SI", "KR", "BD", "PK", "LK", "GH", "KE", "NG", "TZ", "UG", "AG", "AM", "BS", "BB", "BZ", "BT", "BW", "BF", "CV", "CW", "DM", "FJ", "GM", "GE", "GD", "GW", "GY", "HT", "JM", "KI", "LS", "LR", "MW", "MV", "ML", "MH", "FM", "NA", "NR", "NE", "PW", "PG", "PR", "WS", "SM", "ST", "SN", "SC", "SL", "SB", "KN", "LC", "VC", "SR", "TL", "TO", "TT", "TV", "VU", "AZ", "BN", "BI", "KH", "CM", "TD", "KM", "GQ", "SZ", "GA", "GN", "KG", "LA", "MO", "MR", "MN", "NP", "RW", "TG", "UZ", "ZW", "BJ", "MG", "MU", "MZ", "AO", "CI", "DJ", "ZM", "CD", "CG", "IQ", "LY", "TJ", "VE", "ET", "XK"], "disc_number": 1, "duration_ms": 289484, "explicit": true, "external_ids": {"isrc": "HUA612400760"}, "external_urls": {"spotify": "https://open.spotify.com/track/05oBtpki5sMSdRO9tggYuH"}, "href": "https://api.spotify.com/v1/tracks/05oBtpki5sMSdRO9tggYuH", "id": "05oBtpki5sMSdRO9tggYuH", "is_local": false, "name": "10/10", "popularity": 32, "preview_url": null, "track_number": 5, "type": "track", "uri": "spotify:track:05oBtpki5sMSdRO9tggYuH"}