{"album": {"album_type": "single", "artists": [{"external_urls": {"spotify": "https://open.spotify.com/artist/3Vnl7pKDxagUgRJ3NMtEcE"}, "href": "https://api.spotify.com/v1/artists/3Vnl7pKDxagUgRJ3NMtEcE", "id": "3Vnl7pKDxagUgRJ3NMtEcE", "name": "Soufian", "type": "artist", "uri": "spotify:artist:3Vnl7pKDxagUgRJ3NMtEcE"}, {"external_urls": {"spotify": "https://open.spotify.com/artist/3F2BUPEkX9IDaRYAeJN0Gh"}, "href": "https://api.spotify.com/v1/artists/3F2BUPEkX9IDaRYAeJN0Gh", "id": "3F2BUPEkX9IDaRYAeJN0Gh", "name": "Amo", "type": "artist", "uri": "spotify:artist:3F2BUPEkX9IDaRYAeJN0Gh"}, {"external_urls": {"spotify": "https://open.spotify.com/artist/28TqrmNSPiKo5w3WVb3A3N"}, "href": "https://api.spotify.com/v1/artists/28TqrmNSPiKo5w3WVb3A3N", "id": "28TqrmNSPiKo5w3WVb3A3N", "name": "Aymen", "type": "artist", "uri": "spotify:artist:28TqrmNSPiKo5w3WVb3A3N"}], "available_markets": ["AR", "AU", "AT", "BE", "BO", "BR", "BG", "CA", "CL", "CO", "CR", "CY", "CZ", "DK", "DO", "DE", "EC", "EE", "SV", "FI", "FR", "GR", "GT", "HN", "HK", "HU", "IS", "IE", "IT", "LV", "LT", "LU", "MY", "MT", "MX", "NL", "NZ", "NI", "NO", "PA", "PY", "PE", "PH", "PL", "PT", "SG", "SK", "ES", "SE", "CH", "TW", "TR", "UY", "US", "GB", "AD", "LI", "MC", "ID", "JP", "TH", "VN", "RO", "IL", "ZA", "SA", "AE", "BH", "QA", "OM", "KW", "EG", "MA", "DZ", "TN", "LB", "JO", "PS", "IN", "KZ", "MD", "UA", "AL", "BA", "HR", "ME", "MK", "RS", "SI", "KR", "BD", "PK", "LK", "GH", "KE", "NG", "TZ", "UG", "AG", "AM", "BS", "BB", "BZ", "BT", "BW", "BF", "CV", "CW", "DM", "FJ", "GM", "GE", "GD", "GW", "GY", "HT", "JM", "KI", "LS", "LR", "MW", "MV", "ML", "MH", "FM", "NA", "NR", "NE", "PW", "PG", "WS", "SM", "ST", "SN", "SC", "SL", "SB", "KN", "LC", "VC", "SR", "TL", "TO", "TT", "TV", "VU", "AZ", "BN", "BI", "KH", "CM", "TD", "KM", "GQ", "SZ", "GA", "GN", "KG", "LA", "MO", "MR", "MN", "NP", "RW", "TG", "UZ", "ZW", "BJ", "MG", "MU", "MZ", "AO", "CI", "DJ", "ZM", "CD", "CG", "IQ", "LY", "TJ", "VE", "ET", "XK"], "external_urls": {"spotify": "https://open.spotify.com/album/7GhjEYpDQQ8sEGwwBEeuWV"}, "href": "https://api.spotify.com/v1/albums/7GhjEYpDQQ8sEGwwBEeuWV", "id": "7GhjEYpDQQ8sEGwwBEeuWV", "images": [{"url": "https://i.scdn.co/image/ab67616d0000b273a9aa9437e5c641f94e917f47", "width": 640, "height": 640}, {"url": "https://i.scdn.co/image/ab67616d00001e02a9aa9437e5c641f94e917f47", "width": 300, "height": 300}, {"url": "https://i.scdn.co/image/ab67616d00004851a9aa9437e5c641f94e917f47", "width": 64, "height": 64}], "name": "Schlimmer denn je (feat. Amo, Aymen, Nimo x SOTT)", "release_date": "2024-08-08", "release_date_precision": "day", "total_tracks": 1, "type": "album", "uri": "spotify:album:7GhjEYpDQQ8sEGwwBEeuWV"}, "artists": [{"external_urls": {"spotify": "https://open.spotify.com/artist/3Vnl7pKDxagUgRJ3NMtEcE"}, "href": "https://api.spotify.com/v1/artists/3Vnl7pKDxagUgRJ3NMtEcE", "id": "3Vnl7pKDxagUgRJ3NMtEcE", "name": "Soufian", "type": "artist", "uri": "spotify:artist:3Vnl7pKDxagUgRJ3NMtEcE"}, {"external_urls": {"spotify": "https://open.spotify.com/artist/3F2BUPEkX9IDaRYAeJN0Gh"}, "href": "https://api.spotify.com/v1/artists/3F2BUPEkX9IDaRYAeJN0Gh", "id": "3F2BUPEkX9IDaRYAeJN0Gh", "name": "Amo", "type": "artist", "uri": "spotify:artist:3F2BUPEkX9IDaRYAeJN0Gh"}, {"external_urls": {"spotify": "https://open.spotify.com/artist/28TqrmNSPiKo5w3WVb3A3N"}, "href": "https://api.spotify.com/v1/artists/28TqrmNSPiKo5w3WVb3A3N", "id": "28TqrmNSPiKo5w3WVb3A3N", "name": "Aymen", "type": "artist", "uri": "spotify:artist:28TqrmNSPiKo5w3WVb3A3N"}, {"external_urls": {"spotify": "https://open.spotify.com/artist/3ZuBEj9ppJe8GSdKaMTfMN"}, "href": "https://api.spotify.com/v1/artists/3ZuBEj9ppJe8GSdKaMTfMN", "id": "3ZuBEj9ppJe8GSdKaMTfMN", "name": "Nimo", "type": "artist", "uri": "spotify:artist:3ZuBEj9ppJe8GSdKaMTfMN"}, {"external_urls": {"spotify": "https://open.spotify.com/artist/4iusgX5y3xsAn824nywHVI"}, "href": "https://api.spotify.com/v1/artists/4iusgX5y3xsAn824nywHVI", "id": "4iusgX5y3xsAn824nywHVI", "name": "SOTT", "type": "artist", "uri": "spotify:artist:4iusgX5y3xsAn824nywHVI"}], "available_markets": ["AR", "AU", "AT", "BE", "BO", "BR", "BG", "CA", "CL", "CO", "CR", "CY", "CZ", "DK", "DO", "DE", "EC", "EE", "SV", "FI", "FR", "GR", "GT", "HN", "HK", "HU", "IS", "IE", "IT", "LV", "LT", "LU", "MY", "MT", "MX", "NL", "NZ", "NI", "NO", "PA", "PY", "PE", "PH", "PL", "PT", "SG", "SK", "ES", "SE", "CH", "TW", "TR", "UY", "US", "GB", "AD", "LI", "MC", "ID", "JP", "TH", "VN", "RO", "IL", "ZA", "SA", "AE", "BH", "QA", "OM", "KW", "EG", "MA", "DZ", "TN", "LB", "JO", "PS", "IN", "KZ", "MD", "UA", "AL", "BA", "HR", "ME", "MK", "RS", "SI", "KR", "BD", "PK", "LK", "GH", "KE", "NG", "TZ", "UG", "AG", "AM", "BS", "BB", "BZ", "BT", "BW", "BF", "CV", "CW", "DM", "FJ", "GM", "GE", "GD", "GW", "GY", "HT", "JM", "KI", "LS", "LR", "MW", "MV", "ML", "MH", "FM", "NA", "NR", "NE", "PW", "PG", "WS", "SM", "ST", "SN", "SC", "SL", "SB", "KN", "LC", "VC", "SR", "TL", "TO", "TT", "TV", "VU", "AZ", "BN", "BI", "KH", "CM", "TD", "KM", "GQ", "SZ", "GA", "GN", "KG", "LA", "MO", "MR", "MN", "NP", "RW", "TG", "UZ", "ZW", "BJ", "MG", "MU", "MZ", "AO", "CI", "DJ", "ZM", "CD", "CG", "IQ", "LY", "TJ", "VE", "ET", "XK"], "disc_number": 1, "duration_ms": 199087, "explicit": true, "external_ids": {"isrc": "DECE72401567"}, "external_urls": {"spotify": "https://open.spotify.com/track/0aUpHkYuEAT5DZkkuwmS9w"}, "href": "https://api.spotify.com/v1/tracks/0aUpHkYuEAT5DZkkuwmS9w", "id": "0aUpHkYuEAT5DZkkuwmS9w", "is_local": false, "name": "Schlimmer denn je (feat. Amo, Aymen, Nimo x SOTT)", "popularity": 57, "preview_url": null, "track_number": 1, "type": "track", "uri": "spotify:track:0aUpHkYuEAT5DZkkuwmS9w"}