{"album": {"album_type": "single", "artists": [{"external_urls": {"spotify": "https://open.spotify.com/artist/6y1IgqxPpQyqVqwmINNUU2"}, "href": "https://api.spotify.com/v1/artists/6y1IgqxPpQyqVqwmINNUU2", "id": "6y1IgqxPpQyqVqwmINNUU2", "name": "SadBoyForLife", "type": "artist", "uri": "spotify:artist:6y1IgqxPpQyqVqwmINNUU2"}, {"external_urls": {"spotify": "https://open.spotify.com/artist/4eYgQ6qDnzadrMrMOFoXZX"}, "href": "https://api.spotify.com/v1/artists/4eYgQ6qDnzadrMrMOFoXZX", "id": "4eYgQ6qDnzadrMrMOFoXZX", "name": "Skitall", "type": "artist", "uri": "spotify:artist:4eYgQ6qDnzadrMrMOFoXZX"}], "available_markets": [], "external_urls": {"spotify": "https://open.spotify.com/album/4vbtrPiaFIRIoNCYu41ayI"}, "href": "https://api.spotify.com/v1/albums/4vbtrPiaFIRIoNCYu41ayI", "id": "4vbtrPiaFIRIoNCYu41ayI", "images": [{"url": "https://i.scdn.co/image/ab67616d0000b273f041897b53bc6a28578d4264", "width": 640, "height": 640}, {"url": "https://i.scdn.co/image/ab67616d00001e02f041897b53bc6a28578d4264", "width": 300, "height": 300}, {"url": "https://i.scdn.co/image/ab67616d00004851f041897b53bc6a28578d4264", "width": 64, "height": 64}], "name": "olive", "release_date": "2024-06-21", "release_date_precision": "day", "total_tracks": 1, "type": "album", "uri": "spotify:album:4vbtrPiaFIRIoNCYu41ayI"}, "artists": [{"external_urls": {"spotify": "https://open.spotify.com/artist/6y1IgqxPpQyqVqwmINNUU2"}, "href": "https://api.spotify.com/v1/artists/6y1IgqxPpQyqVqwmINNUU2", "id": "6y1IgqxPpQyqVqwmINNUU2", "name": "SadBoyForLife", "type": "artist", "uri": "spotify:artist:6y1IgqxPpQyqVqwmINNUU2"}, {"external_urls": {"spotify": "https://open.spotify.com/artist/4eYgQ6qDnzadrMrMOFoXZX"}, "href": "https://api.spotify.com/v1/artists/4eYgQ6qDnzadrMrMOFoXZX", "id": "4eYgQ6qDnzadrMrMOFoXZX", "name": "Skitall", "type": "artist", "uri": "spotify:artist:4eYgQ6qDnzadrMrMOFoXZX"}], "available_markets": [], "disc_number": 1, "duration_ms": 141176, "explicit": true, "external_ids": {"isrc": "SE6HN2412498"}, "external_urls": {"spotify": "https://open.spotify.com/track/0MWhR7u9YBRraRPCZl0TXg"}, "href": "https://api.spotify.com/v1/tracks/0MWhR7u9YBRraRPCZl0TXg", "id": "0MWhR7u9YBRraRPCZl0TXg", "is_local": false, "name": "olive", "popularity": 1, "preview_url": null, "track_number": 1, "type": "track", "uri": "spotify:track:0MWhR7u9YBRraRPCZl0TXg"}