{"album": {"album_type": "single", "artists": [{"external_urls": {"spotify": "https://open.spotify.com/artist/5oNWzcU0mYK1zDUxBGHIaG"}, "href": "https://api.spotify.com/v1/artists/5oNWzcU0mYK1zDUxBGHIaG", "id": "5oNWzcU0mYK1zDUxBGHIaG", "name": "Hannah Mae", "type": "artist", "uri": "spotify:artist:5oNWzcU0mYK1zDUxBGHIaG"}], "available_markets": [], "external_urls": {"spotify": "https://open.spotify.com/album/6RB3yTXoYgKACU6TCqj9qa"}, "href": "https://api.spotify.com/v1/albums/6RB3yTXoYgKACU6TCqj9qa", "id": "6RB3yTXoYgKACU6TCqj9qa", "images": [{"url": "https://i.scdn.co/image/ab67616d0000b27328fa79c4e5fe982abf9bb521", "width": 640, "height": 640}, {"url": "https://i.scdn.co/image/ab67616d00001e0228fa79c4e5fe982abf9bb521", "width": 300, "height": 300}, {"url": "https://i.scdn.co/image/ab67616d0000485128fa79c4e5fe982abf9bb521", "width": 64, "height": 64}], "name": "Waterdicht", "release_date": "2023-10-20", "release_date_precision": "day", "total_tracks": 2, "type": "album", "uri": "spotify:album:6RB3yTXoYgKACU6TCqj9qa"}, "artists": [{"external_urls": {"spotify": "https://open.spotify.com/artist/5oNWzcU0mYK1zDUxBGHIaG"}, "href": "https://api.spotify.com/v1/artists/5oNWzcU0mYK1zDUxBGHIaG", "id": "5oNWzcU0mYK1zDUxBGHIaG", "name": "Hannah Mae", "type": "artist", "uri": "spotify:artist:5oNWzcU0mYK1zDUxBGHIaG"}], "available_markets": [], "disc_number": 1, "duration_ms": 171932, "explicit": false, "external_ids": {"isrc": "NL1TK2300022"}, "external_urls": {"spotify": "https://open.spotify.com/track/1guLggb4orDoc7Dmh2cSuL"}, "href": "https://api.spotify.com/v1/tracks/1guLggb4orDoc7Dmh2cSuL", "id": "1guLggb4orDoc7Dmh2cSuL", "is_local": false, "name": "Waterdicht", "popularity": 34, "preview_url": null, "track_number": 1, "type": "track", "uri": "spotify:track:1guLggb4orDoc7Dmh2cSuL"}