{"album": {"album_type": "single", "artists": [{"external_urls": {"spotify": "https://open.spotify.com/artist/6zO1dZ40fTZ5hY9NnnRJSk"}, "href": "https://api.spotify.com/v1/artists/6zO1dZ40fTZ5hY9NnnRJSk", "id": "6zO1dZ40fTZ5hY9NnnRJSk", "name": "yung kai", "type": "artist", "uri": "spotify:artist:6zO1dZ40fTZ5hY9NnnRJSk"}], "available_markets": [], "external_urls": {"spotify": "https://open.spotify.com/album/4dhoGa2hqBQ402BaIwBpcn"}, "href": "https://api.spotify.com/v1/albums/4dhoGa2hqBQ402BaIwBpcn", "id": "4dhoGa2hqBQ402BaIwBpcn", "images": [{"url": "https://i.scdn.co/image/ab67616d0000b2732c78500833c22279f8bef841", "width": 640, "height": 640}, {"url": "https://i.scdn.co/image/ab67616d00001e022c78500833c22279f8bef841", "width": 300, "height": 300}, {"url": "https://i.scdn.co/image/ab67616d000048512c78500833c22279f8bef841", "width": 64, "height": 64}], "name": "blue", "release_date": "2024-08-02", "release_date_precision": "day", "total_tracks": 1, "type": "album", "uri": "spotify:album:4dhoGa2hqBQ402BaIwBpcn"}, "artists": [{"external_urls": {"spotify": "https://open.spotify.com/artist/6zO1dZ40fTZ5hY9NnnRJSk"}, "href": "https://api.spotify.com/v1/artists/6zO1dZ40fTZ5hY9NnnRJSk", "id": "6zO1dZ40fTZ5hY9NnnRJSk", "name": "yung kai", "type": "artist", "uri": "spotify:artist:6zO1dZ40fTZ5hY9NnnRJSk"}], "available_markets": [], "disc_number": 1, "duration_ms": 214357, "explicit": false, "external_ids": {"isrc": "TLVEM2456474"}, "external_urls": {"spotify": "https://open.spotify.com/track/2ezMnGfGww3WSOJp7TwI1N"}, "href": "https://api.spotify.com/v1/tracks/2ezMnGfGww3WSOJp7TwI1N", "id": "2ezMnGfGww3WSOJp7TwI1N", "is_local": false, "name": "blue", "popularity": 68, "preview_url": null, "track_number": 1, "type": "track", "uri": "spotify:track:2ezMnGfGww3WSOJp7TwI1N"}