{"album": {"album_type": "single", "artists": [{"external_urls": {"spotify": "https://open.spotify.com/artist/58CkoIvSDda2jNRipPe4oT"}, "href": "https://api.spotify.com/v1/artists/58CkoIvSDda2jNRipPe4oT", "id": "58CkoIvSDda2jNRipPe4oT", "name": "Rubby", "type": "artist", "uri": "spotify:artist:58CkoIvSDda2jNRipPe4oT"}], "available_markets": [], "external_urls": {"spotify": "https://open.spotify.com/album/2DMwzpbbhllY9aqZvwGZSJ"}, "href": "https://api.spotify.com/v1/albums/2DMwzpbbhllY9aqZvwGZSJ", "id": "2DMwzpbbhllY9aqZvwGZSJ", "images": [{"url": "https://i.scdn.co/image/ab67616d0000b273ffe942ca22da70d7d84a1815", "width": 640, "height": 640}, {"url": "https://i.scdn.co/image/ab67616d00001e02ffe942ca22da70d7d84a1815", "width": 300, "height": 300}, {"url": "https://i.scdn.co/image/ab67616d00004851ffe942ca22da70d7d84a1815", "width": 64, "height": 64}], "name": "Sou Baiana", "release_date": "2024-07-22", "release_date_precision": "day", "total_tracks": 1, "type": "album", "uri": "spotify:album:2DMwzpbbhllY9aqZvwGZSJ"}, "artists": [{"external_urls": {"spotify": "https://open.spotify.com/artist/58CkoIvSDda2jNRipPe4oT"}, "href": "https://api.spotify.com/v1/artists/58CkoIvSDda2jNRipPe4oT", "id": "58CkoIvSDda2jNRipPe4oT", "name": "Rubby", "type": "artist", "uri": "spotify:artist:58CkoIvSDda2jNRipPe4oT"}], "available_markets": [], "disc_number": 1, "duration_ms": 137000, "explicit": false, "external_ids": {"isrc": "GXD7V2212480"}, "external_urls": {"spotify": "https://open.spotify.com/track/2jOOrtPppgKV7ELxy4KmpD"}, "href": "https://api.spotify.com/v1/tracks/2jOOrtPppgKV7ELxy4KmpD", "id": "2jOOrtPppgKV7ELxy4KmpD", "is_local": false, "name": "Sou Baiana", "popularity": 56, "preview_url": null, "track_number": 1, "type": "track", "uri": "spotify:track:2jOOrtPppgKV7ELxy4KmpD"}