{"album": {"album_type": "single", "artists": [{"external_urls": {"spotify": "https://open.spotify.com/artist/11HepfI1lj6KJHj651rZhM"}, "href": "https://api.spotify.com/v1/artists/11HepfI1lj6KJHj651rZhM", "id": "11HepfI1lj6KJHj651rZhM", "name": "Lucky Brown", "type": "artist", "uri": "spotify:artist:11HepfI1lj6KJHj651rZhM"}], "available_markets": [], "external_urls": {"spotify": "https://open.spotify.com/album/2wZGGuDMF3MsvjCky3oOMy"}, "href": "https://api.spotify.com/v1/albums/2wZGGuDMF3MsvjCky3oOMy", "id": "2wZGGuDMF3MsvjCky3oOMy", "images": [{"url": "https://i.scdn.co/image/ab67616d0000b273f876e95508ecf528440cd758", "width": 640, "height": 640}, {"url": "https://i.scdn.co/image/ab67616d00001e02f876e95508ecf528440cd758", "width": 300, "height": 300}, {"url": "https://i.scdn.co/image/ab67616d00004851f876e95508ecf528440cd758", "width": 64, "height": 64}], "name": "Sola Suelta Soltera", "release_date": "2024-07-25", "release_date_precision": "day", "total_tracks": 1, "type": "album", "uri": "spotify:album:2wZGGuDMF3MsvjCky3oOMy"}, "artists": [{"external_urls": {"spotify": "https://open.spotify.com/artist/11HepfI1lj6KJHj651rZhM"}, "href": "https://api.spotify.com/v1/artists/11HepfI1lj6KJHj651rZhM", "id": "11HepfI1lj6KJHj651rZhM", "name": "Lucky Brown", "type": "artist", "uri": "spotify:artist:11HepfI1lj6KJHj651rZhM"}, {"external_urls": {"spotify": "https://open.spotify.com/artist/07WSqyexqFJM0ZeQVPqJJg"}, "href": "https://api.spotify.com/v1/artists/07WSqyexqFJM0ZeQVPqJJg", "id": "07WSqyexqFJM0ZeQVPqJJg", "name": "Mateo on the Beatz", "type": "artist", "uri": "spotify:artist:07WSqyexqFJM0ZeQVPqJJg"}], "available_markets": [], "disc_number": 1, "duration_ms": 163200, "explicit": false, "external_ids": {"isrc": "CLA1D2400070"}, "external_urls": {"spotify": "https://open.spotify.com/track/2TsQ2eMg44sEqvbLwjzWrA"}, "href": "https://api.spotify.com/v1/tracks/2TsQ2eMg44sEqvbLwjzWrA", "id": "2TsQ2eMg44sEqvbLwjzWrA", "is_local": false, "name": "Sola Suelta Soltera", "popularity": 35, "preview_url": null, "track_number": 1, "type": "track", "uri": "spotify:track:2TsQ2eMg44sEqvbLwjzWrA"}