{"album": {"album_type": "single", "artists": [{"external_urls": {"spotify": "https://open.spotify.com/artist/4KGzrDuN7l1lrMNuio2fUe"}, "href": "https://api.spotify.com/v1/artists/4KGzrDuN7l1lrMNuio2fUe", "id": "4KGzrDuN7l1lrMNuio2fUe", "name": "yousef mohamed", "type": "artist", "uri": "spotify:artist:4KGzrDuN7l1lrMNuio2fUe"}], "available_markets": [], "external_urls": {"spotify": "https://open.spotify.com/album/7pMR8laKUlwWAornFEEA57"}, "href": "https://api.spotify.com/v1/albums/7pMR8laKUlwWAornFEEA57", "id": "7pMR8laKUlwWAornFEEA57", "images": [{"url": "https://i.scdn.co/image/ab67616d0000b273d6d89e3712bcb79181bbec96", "width": 640, "height": 640}, {"url": "https://i.scdn.co/image/ab67616d00001e02d6d89e3712bcb79181bbec96", "width": 300, "height": 300}, {"url": "https://i.scdn.co/image/ab67616d00004851d6d89e3712bcb79181bbec96", "width": 64, "height": 64}], "name": "\u0644\u0639\u0628\u0627\u0644\u064a \u0641\u064a \u062f\u0645\u0627\u063a\u064a", "release_date": "2024-10-10", "release_date_precision": "day", "total_tracks": 1, "type": "album", "uri": "spotify:album:7pMR8laKUlwWAornFEEA57"}, "artists": [{"external_urls": {"spotify": "https://open.spotify.com/artist/4KGzrDuN7l1lrMNuio2fUe"}, "href": "https://api.spotify.com/v1/artists/4KGzrDuN7l1lrMNuio2fUe", "id": "4KGzrDuN7l1lrMNuio2fUe", "name": "yousef mohamed", "type": "artist", "uri": "spotify:artist:4KGzrDuN7l1lrMNuio2fUe"}, {"external_urls": {"spotify": "https://open.spotify.com/artist/5QKGejJMncXUNUb9pUFbEf"}, "href": "https://api.spotify.com/v1/artists/5QKGejJMncXUNUb9pUFbEf", "id": "5QKGejJMncXUNUb9pUFbEf", "name": "TUL8TE", "type": "artist", "uri": "spotify:artist:5QKGejJMncXUNUb9pUFbEf"}], "available_markets": [], "disc_number": 1, "duration_ms": 142477, "explicit": true, "external_ids": {"isrc": "SE5XG2445841"}, "external_urls": {"spotify": "https://open.spotify.com/track/37FL23FnskUH9np0LiM5bL"}, "href": "https://api.spotify.com/v1/tracks/37FL23FnskUH9np0LiM5bL", "id": "37FL23FnskUH9np0LiM5bL", "is_local": false, "name": "\u0644\u0639\u0628\u0627\u0644\u064a \u0641\u064a \u062f\u0645\u0627\u063a\u064a", "popularity": 47, "preview_url": null, "track_number": 1, "type": "track", "uri": "spotify:track:37FL23FnskUH9np0LiM5bL"}