{"album": {"album_type": "album", "artists": [{"external_urls": {"spotify": "https://open.spotify.com/artist/3fMbdgg4jU18AjLCKBhRSm"}, "href": "https://api.spotify.com/v1/artists/3fMbdgg4jU18AjLCKBhRSm", "id": "3fMbdgg4jU18AjLCKBhRSm", "name": "Michael Jackson", "type": "artist", "uri": "spotify:artist:3fMbdgg4jU18AjLCKBhRSm"}], "available_markets": ["AR", "AU", "AT", "BE", "BO", "BR", "BG", "CA", "CL", "CO", "CR", "CY", "CZ", "DK", "DO", "DE", "EC", "EE", "SV", "FI", "FR", "GR", "GT", "HN", "HK", "HU", "IS", "IE", "IT", "LV", "LT", "LU", "MY", "MT", "MX", "NL", "NZ", "NI", "NO", "PA", "PY", "PE", "PH", "PL", "PT", "SG", "SK", "ES", "SE", "CH", "TW", "TR", "UY", "US", "GB", "AD", "LI", "MC", "ID", "JP", "TH", "VN", "RO", "IL", "ZA", "SA", "AE", "BH", "QA", "OM", "KW", "EG", "MA", "DZ", "TN", "LB", "JO", "PS", "IN", "BY", "KZ", "MD", "UA", "AL", "BA", "HR", "ME", "MK", "RS", "SI", "KR", "BD", "PK", "LK", "GH", "KE", "NG", "TZ", "UG", "AG", "AM", "BS", "BB", "BZ", "BT", "BW", "BF", "CV", "CW", "DM", "FJ", "GM", "GE", "GD", "GW", "GY", "HT", "JM", "KI", "LS", "LR", "MW", "MV", "ML", "MH", "FM", "NA", "NR", "NE", "PW", "PG", "PR", "WS", "SM", "ST", "SN", "SC", "SL", "SB", "KN", "LC", "VC", "SR", "TL", "TO", "TT", "TV", "VU", "AZ", "BN", "BI", "KH", "CM", "TD", "KM", "GQ", "SZ", "GA", "GN", "KG", "LA", "MO", "MR", "MN", "NP", "RW", "TG", "UZ", "ZW", "BJ", "MG", "MU", "MZ", "AO", "CI", "DJ", "ZM", "CD", "CG", "IQ", "LY", "TJ", "VE", "ET", "XK"], "external_urls": {"spotify": "https://open.spotify.com/album/2ANVost0y2y52ema1E9xAZ"}, "href": "https://api.spotify.com/v1/albums/2ANVost0y2y52ema1E9xAZ", "id": "2ANVost0y2y52ema1E9xAZ", "images": [{"url": "https://i.scdn.co/image/ab67616d0000b273de437d960dda1ac0a3586d97", "width": 640, "height": 640}, {"url": "https://i.scdn.co/image/ab67616d00001e02de437d960dda1ac0a3586d97", "width": 300, "height": 300}, {"url": "https://i.scdn.co/image/ab67616d00004851de437d960dda1ac0a3586d97", "width": 64, "height": 64}], "name": "Thriller", "release_date": "1982-11-30", "release_date_precision": "day", "total_tracks": 9, "type": "album", "uri": "spotify:album:2ANVost0y2y52ema1E9xAZ"}, "artists": [{"external_urls": {"spotify": "https://open.spotify.com/artist/3fMbdgg4jU18AjLCKBhRSm"}, "href": "https://api.spotify.com/v1/artists/3fMbdgg4jU18AjLCKBhRSm", "id": "3fMbdgg4jU18AjLCKBhRSm", "name": "Michael Jackson", "type": "artist", "uri": "spotify:artist:3fMbdgg4jU18AjLCKBhRSm"}], "available_markets": ["AR", "AU", "AT", "BE", "BO", "BR", "BG", "CA", "CL", "CO", "CR", "CY", "CZ", "DK", "DO", "DE", "EC", "EE", "SV", "FI", "FR", "GR", "GT", "HN", "HK", "HU", "IS", "IE", "IT", "LV", "LT", "LU", "MY", "MT", "MX", "NL", "NZ", "NI", "NO", "PA", "PY", "PE", "PH", "PL", "PT", "SG", "SK", "ES", "SE", "CH", "TW", "TR", "UY", "US", "GB", "AD", "LI", "MC", "ID", "JP", "TH", "VN", "RO", "IL", "ZA", "SA", "AE", "BH", "QA", "OM", "KW", "EG", "MA", "DZ", "TN", "LB", "JO", "PS", "IN", "BY", "KZ", "MD", "UA", "AL", "BA", "HR", "ME", "MK", "RS", "SI", "KR", "BD", "PK", "LK", "GH", "KE", "NG", "TZ", "UG", "AG", "AM", "BS", "BB", "BZ", "BT", "BW", "BF", "CV", "CW", "DM", "FJ", "GM", "GE", "GD", "GW", "GY", "HT", "JM", "KI", "LS", "LR", "MW", "MV", "ML", "MH", "FM", "NA", "NR", "NE", "PW", "PG", "PR", "WS", "SM", "ST", "SN", "SC", "SL", "SB", "KN", "LC", "VC", "SR", "TL", "TO", "TT", "TV", "VU", "AZ", "BN", "BI", "KH", "CM", "TD", "KM", "GQ", "SZ", "GA", "GN", "KG", "LA", "MO", "MR", "MN", "NP", "RW", "TG", "UZ", "ZW", "BJ", "MG", "MU", "MZ", "AO", "CI", "DJ", "ZM", "CD", "CG", "IQ", "LY", "TJ", "VE", "ET", "XK"], "disc_number": 1, "duration_ms": 258399, "explicit": false, "external_ids": {"isrc": "USSM19902990"}, "external_urls": {"spotify": "https://open.spotify.com/track/3BovdzfaX4jb5KFQwoPfAw"}, "href": "https://api.spotify.com/v1/tracks/3BovdzfaX4jb5KFQwoPfAw", "id": "3BovdzfaX4jb5KFQwoPfAw", "is_local": false, "name": "Beat It", "popularity": 79, "preview_url": null, "track_number": 5, "type": "track", "uri": "spotify:track:3BovdzfaX4jb5KFQwoPfAw"}