{"album": {"album_type": "single", "artists": [{"external_urls": {"spotify": "https://open.spotify.com/artist/5qSwpcWU98AJITpF4USeC3"}, "href": "https://api.spotify.com/v1/artists/5qSwpcWU98AJITpF4USeC3", "id": "5qSwpcWU98AJITpF4USeC3", "name": "Isabel Aai\u00fan", "type": "artist", "uri": "spotify:artist:5qSwpcWU98AJITpF4USeC3"}, {"external_urls": {"spotify": "https://open.spotify.com/artist/4TQTQKrC6eNENv4xSH3Ax6"}, "href": "https://api.spotify.com/v1/artists/4TQTQKrC6eNENv4xSH3Ax6", "id": "4TQTQKrC6eNENv4xSH3Ax6", "name": "Fernando Moreno", "type": "artist", "uri": "spotify:artist:4TQTQKrC6eNENv4xSH3Ax6"}], "available_markets": ["AR", "AU", "AT", "BE", "BO", "BR", "BG", "CA", "CL", "CO", "CR", "CY", "CZ", "DK", "DO", "DE", "EC", "EE", "SV", "FI", "FR", "GR", "GT", "HN", "HK", "HU", "IS", "IE", "IT", "LV", "LT", "LU", "MY", "MT", "MX", "NL", "NZ", "NI", "NO", "PA", "PY", "PE", "PH", "PL", "PT", "SG", "SK", "ES", "SE", "CH", "TW", "TR", "UY", "US", "GB", "AD", "LI", "MC", "ID", "JP", "TH", "VN", "RO", "IL", "ZA", "SA", "AE", "BH", "QA", "OM", "KW", "EG", "MA", "DZ", "TN", "LB", "JO", "PS", "IN", "BY", "KZ", "MD", "UA", "AL", "BA", "HR", "ME", "MK", "RS", "SI", "KR", "BD", "PK", "LK", "GH", "KE", "NG", "TZ", "UG", "AG", "AM", "BS", "BB", "BZ", "BT", "BW", "BF", "CV", "CW", "DM", "FJ", "GM", "GE", "GD", "GW", "GY", "HT", "JM", "KI", "LS", "LR", "MW", "MV", "ML", "MH", "FM", "NA", "NR", "NE", "PW", "PG", "PR", "WS", "SM", "ST", "SN", "SC", "SL", "SB", "KN", "LC", "VC", "SR", "TL", "TO", "TT", "TV", "VU", "AZ", "BN", "BI", "KH", "CM", "TD", "KM", "GQ", "SZ", "GA", "GN", "KG", "LA", "MO", "MR", "MN", "NP", "RW", "TG", "UZ", "ZW", "BJ", "MG", "MU", "MZ", "AO", "CI", "DJ", "ZM", "CD", "CG", "IQ", "LY", "TJ", "VE", "ET", "XK"], "external_urls": {"spotify": "https://open.spotify.com/album/7ztKmDnGDBWN0aFhuwXRfW"}, "href": "https://api.spotify.com/v1/albums/7ztKmDnGDBWN0aFhuwXRfW", "id": "7ztKmDnGDBWN0aFhuwXRfW", "images": [{"url": "https://i.scdn.co/image/ab67616d0000b27340b1d6f6201f92d7f4accc0c", "width": 640, "height": 640}, {"url": "https://i.scdn.co/image/ab67616d00001e0240b1d6f6201f92d7f4accc0c", "width": 300, "height": 300}, {"url": "https://i.scdn.co/image/ab67616d0000485140b1d6f6201f92d7f4accc0c", "width": 64, "height": 64}], "name": "Potra Salvaje (Hard Remix)", "release_date": "2023-10-14", "release_date_precision": "day", "total_tracks": 1, "type": "album", "uri": "spotify:album:7ztKmDnGDBWN0aFhuwXRfW"}, "artists": [{"external_urls": {"spotify": "https://open.spotify.com/artist/5qSwpcWU98AJITpF4USeC3"}, "href": "https://api.spotify.com/v1/artists/5qSwpcWU98AJITpF4USeC3", "id": "5qSwpcWU98AJITpF4USeC3", "name": "Isabel Aai\u00fan", "type": "artist", "uri": "spotify:artist:5qSwpcWU98AJITpF4USeC3"}, {"external_urls": {"spotify": "https://open.spotify.com/artist/4TQTQKrC6eNENv4xSH3Ax6"}, "href": "https://api.spotify.com/v1/artists/4TQTQKrC6eNENv4xSH3Ax6", "id": "4TQTQKrC6eNENv4xSH3Ax6", "name": "Fernando Moreno", "type": "artist", "uri": "spotify:artist:4TQTQKrC6eNENv4xSH3Ax6"}], "available_markets": ["AR", "AU", "AT", "BE", "BO", "BR", "BG", "CA", "CL", "CO", "CR", "CY", "CZ", "DK", "DO", "DE", "EC", "EE", "SV", "FI", "FR", "GR", "GT", "HN", "HK", "HU", "IS", "IE", "IT", "LV", "LT", "LU", "MY", "MT", "MX", "NL", "NZ", "NI", "NO", "PA", "PY", "PE", "PH", "PL", "PT", "SG", "SK", "ES", "SE", "CH", "TW", "TR", "UY", "US", "GB", "AD", "LI", "MC", "ID", "JP", "TH", "VN", "RO", "IL", "ZA", "SA", "AE", "BH", "QA", "OM", "KW", "EG", "MA", "DZ", "TN", "LB", "JO", "PS", "IN", "BY", "KZ", "MD", "UA", "AL", "BA", "HR", "ME", "MK", "RS", "SI", "KR", "BD", "PK", "LK", "GH", "KE", "NG", "TZ", "UG", "AG", "AM", "BS", "BB", "BZ", "BT", "BW", "BF", "CV", "CW", "DM", "FJ", "GM", "GE", "GD", "GW", "GY", "HT", "JM", "KI", "LS", "LR", "MW", "MV", "ML", "MH", "FM", "NA", "NR", "NE", "PW", "PG", "PR", "WS", "SM", "ST", "SN", "SC", "SL", "SB", "KN", "LC", "VC", "SR", "TL", "TO", "TT", "TV", "VU", "AZ", "BN", "BI", "KH", "CM", "TD", "KM", "GQ", "SZ", "GA", "GN", "KG", "LA", "MO", "MR", "MN", "NP", "RW", "TG", "UZ", "ZW", "BJ", "MG", "MU", "MZ", "AO", "CI", "DJ", "ZM", "CD", "CG", "IQ", "LY", "TJ", "VE", "ET", "XK"], "disc_number": 1, "duration_ms": 342000, "explicit": false, "external_ids": {"isrc": "QZTB82355610"}, "external_urls": {"spotify": "https://open.spotify.com/track/4gdpQ6zuDsePnD1YIDJCRw"}, "href": "https://api.spotify.com/v1/tracks/4gdpQ6zuDsePnD1YIDJCRw", "id": "4gdpQ6zuDsePnD1YIDJCRw", "is_local": false, "name": "Potra Salvaje - Hard Remix", "popularity": 65, "preview_url": null, "track_number": 1, "type": "track", "uri": "spotify:track:4gdpQ6zuDsePnD1YIDJCRw"}