{"album": {"album_type": "single", "artists": [{"external_urls": {"spotify": "https://open.spotify.com/artist/3LtYMPncqtiugGwOuuLq3h"}, "href": "https://api.spotify.com/v1/artists/3LtYMPncqtiugGwOuuLq3h", "id": "3LtYMPncqtiugGwOuuLq3h", "name": "Baddiel, Skinner & Lightning Seeds", "type": "artist", "uri": "spotify:artist:3LtYMPncqtiugGwOuuLq3h"}], "available_markets": ["AR", "AU", "AT", "BE", "BO", "BR", "BG", "CA", "CL", "CO", "CR", "CY", "CZ", "DK", "DO", "DE", "EC", "EE", "SV", "FI", "FR", "GR", "GT", "HN", "HK", "HU", "IS", "IE", "IT", "LV", "LT", "LU", "MY", "MT", "MX", "NL", "NZ", "NI", "NO", "PA", "PY", "PE", "PH", "PL", "PT", "SG", "SK", "ES", "SE", "CH", "TW", "TR", "UY", "US", "GB", "AD", "LI", "MC", "ID", "JP", "TH", "VN", "RO", "IL", "ZA", "SA", "AE", "BH", "QA", "OM", "KW", "EG", "MA", "DZ", "TN", "LB", "JO", "PS", "IN", "BY", "KZ", "MD", "UA", "AL", "BA", "HR", "ME", "MK", "RS", "SI", "KR", "BD", "PK", "LK", "GH", "KE", "NG", "TZ", "UG", "AG", "AM", "BS", "BB", "BZ", "BT", "BW", "BF", "CV", "CW", "DM", "FJ", "GM", "GE", "GD", "GW", "GY", "HT", "JM", "KI", "LS", "LR", "MW", "MV", "ML", "MH", "FM", "NA", "NR", "NE", "PW", "PG", "PR", "WS", "SM", "ST", "SN", "SC", "SL", "SB", "KN", "LC", "VC", "SR", "TL", "TO", "TT", "TV", "VU", "AZ", "BN", "BI", "KH", "CM", "TD", "KM", "GQ", "SZ", "GA", "GN", "KG", "LA", "MO", "MR", "MN", "NP", "RW", "TG", "UZ", "ZW", "BJ", "MG", "MU", "MZ", "AO", "CI", "DJ", "ZM", "CD", "CG", "IQ", "LY", "TJ", "VE", "ET", "XK"], "external_urls": {"spotify": "https://open.spotify.com/album/4g9hgB2Y0kG4eQbeDNq5OT"}, "href": "https://api.spotify.com/v1/albums/4g9hgB2Y0kG4eQbeDNq5OT", "id": "4g9hgB2Y0kG4eQbeDNq5OT", "images": [{"url": "https://i.scdn.co/image/ab67616d0000b2734fb86cf461e0bf99bdbabd81", "width": 640, "height": 640}, {"url": "https://i.scdn.co/image/ab67616d00001e024fb86cf461e0bf99bdbabd81", "width": 300, "height": 300}, {"url": "https://i.scdn.co/image/ab67616d000048514fb86cf461e0bf99bdbabd81", "width": 64, "height": 64}], "name": "Three Lions (It's Coming Home for Christmas)", "release_date": "2022-11-18", "release_date_precision": "day", "total_tracks": 3, "type": "album", "uri": "spotify:album:4g9hgB2Y0kG4eQbeDNq5OT"}, "artists": [{"external_urls": {"spotify": "https://open.spotify.com/artist/3LtYMPncqtiugGwOuuLq3h"}, "href": "https://api.spotify.com/v1/artists/3LtYMPncqtiugGwOuuLq3h", "id": "3LtYMPncqtiugGwOuuLq3h", "name": "Baddiel, Skinner & Lightning Seeds", "type": "artist", "uri": "spotify:artist:3LtYMPncqtiugGwOuuLq3h"}, {"external_urls": {"spotify": "https://open.spotify.com/artist/67YNiSqhrx1P8oPvIIvbP5"}, "href": "https://api.spotify.com/v1/artists/67YNiSqhrx1P8oPvIIvbP5", "id": "67YNiSqhrx1P8oPvIIvbP5", "name": "The Lightning Seeds", "type": "artist", "uri": "spotify:artist:67YNiSqhrx1P8oPvIIvbP5"}], "available_markets": ["AR", "AU", "AT", "BE", "BO", "BR", "BG", "CA", "CL", "CO", "CR", "CY", "CZ", "DK", "DO", "DE", "EC", "EE", "SV", "FI", "FR", "GR", "GT", "HN", "HK", "HU", "IS", "IE", "IT", "LV", "LT", "LU", "MY", "MT", "MX", "NL", "NZ", "NI", "NO", "PA", "PY", "PE", "PH", "PL", "PT", "SG", "SK", "ES", "SE", "CH", "TW", "TR", "UY", "US", "GB", "AD", "LI", "MC", "ID", "JP", "TH", "VN", "RO", "IL", "ZA", "SA", "AE", "BH", "QA", "OM", "KW", "EG", "MA", "DZ", "TN", "LB", "JO", "PS", "IN", "BY", "KZ", "MD", "UA", "AL", "BA", "HR", "ME", "MK", "RS", "SI", "KR", "BD", "PK", "LK", "GH", "KE", "NG", "TZ", "UG", "AG", "AM", "BS", "BB", "BZ", "BT", "BW", "BF", "CV", "CW", "DM", "FJ", "GM", "GE", "GD", "GW", "GY", "HT", "JM", "KI", "LS", "LR", "MW", "MV", "ML", "MH", "FM", "NA", "NR", "NE", "PW", "PG", "PR", "WS", "SM", "ST", "SN", "SC", "SL", "SB", "KN", "LC", "VC", "SR", "TL", "TO", "TT", "TV", "VU", "AZ", "BN", "BI", "KH", "CM", "TD", "KM", "GQ", "SZ", "GA", "GN", "KG", "LA", "MO", "MR", "MN", "NP", "RW", "TG", "UZ", "ZW", "BJ", "MG", "MU", "MZ", "AO", "CI", "DJ", "ZM", "CD", "CG", "IQ", "LY", "TJ", "VE", "ET", "XK"], "disc_number": 1, "duration_ms": 240292, "explicit": false, "external_ids": {"isrc": "GBARL2201601"}, "external_urls": {"spotify": "https://open.spotify.com/track/54tDU1G1SLTAtRvRFltqvJ"}, "href": "https://api.spotify.com/v1/tracks/54tDU1G1SLTAtRvRFltqvJ", "id": "54tDU1G1SLTAtRvRFltqvJ", "is_local": false, "name": "Three Lions 98 - Remastered", "popularity": 33, "preview_url": null, "track_number": 3, "type": "track", "uri": "spotify:track:54tDU1G1SLTAtRvRFltqvJ"}