{"album": {"album_type": "single", "artists": [{"external_urls": {"spotify": "https://open.spotify.com/artist/3tLXPx5dsnZtsodGSf6t8E"}, "href": "https://api.spotify.com/v1/artists/3tLXPx5dsnZtsodGSf6t8E", "id": "3tLXPx5dsnZtsodGSf6t8E", "name": "Chris Jonex", "type": "artist", "uri": "spotify:artist:3tLXPx5dsnZtsodGSf6t8E"}], "available_markets": [], "external_urls": {"spotify": "https://open.spotify.com/album/6IPSnKh21CZDtRnUbBwvwr"}, "href": "https://api.spotify.com/v1/albums/6IPSnKh21CZDtRnUbBwvwr", "id": "6IPSnKh21CZDtRnUbBwvwr", "images": [{"url": "https://i.scdn.co/image/ab67616d0000b2732d5c2d20bbcec5f254a069fa", "width": 640, "height": 640}, {"url": "https://i.scdn.co/image/ab67616d00001e022d5c2d20bbcec5f254a069fa", "width": 300, "height": 300}, {"url": "https://i.scdn.co/image/ab67616d000048512d5c2d20bbcec5f254a069fa", "width": 64, "height": 64}], "name": "Chanel", "release_date": "2023-11-03", "release_date_precision": "day", "total_tracks": 1, "type": "album", "uri": "spotify:album:6IPSnKh21CZDtRnUbBwvwr"}, "artists": [{"external_urls": {"spotify": "https://open.spotify.com/artist/3tLXPx5dsnZtsodGSf6t8E"}, "href": "https://api.spotify.com/v1/artists/3tLXPx5dsnZtsodGSf6t8E", "id": "3tLXPx5dsnZtsodGSf6t8E", "name": "Chris Jonex", "type": "artist", "uri": "spotify:artist:3tLXPx5dsnZtsodGSf6t8E"}, {"external_urls": {"spotify": "https://open.spotify.com/artist/5nDA5BYRYBo92lTzCECLhA"}, "href": "https://api.spotify.com/v1/artists/5nDA5BYRYBo92lTzCECLhA", "id": "5nDA5BYRYBo92lTzCECLhA", "name": "Eme Santana", "type": "artist", "uri": "spotify:artist:5nDA5BYRYBo92lTzCECLhA"}], "available_markets": [], "disc_number": 1, "duration_ms": 122164, "explicit": false, "external_ids": {"isrc": "BK4DA2320811"}, "external_urls": {"spotify": "https://open.spotify.com/track/5B0vGlnXGZH53v8W3RZavf"}, "href": "https://api.spotify.com/v1/tracks/5B0vGlnXGZH53v8W3RZavf", "id": "5B0vGlnXGZH53v8W3RZavf", "is_local": false, "name": "Chanel (feat. Eme Santana)", "popularity": 0, "preview_url": null, "track_number": 1, "type": "track", "uri": "spotify:track:5B0vGlnXGZH53v8W3RZavf"}