{"album": {"album_type": "single", "artists": [{"external_urls": {"spotify": "https://open.spotify.com/artist/6dOAGo4z0syiCjbnlh4VSO"}, "href": "https://api.spotify.com/v1/artists/6dOAGo4z0syiCjbnlh4VSO", "id": "6dOAGo4z0syiCjbnlh4VSO", "name": "Critical", "type": "artist", "uri": "spotify:artist:6dOAGo4z0syiCjbnlh4VSO"}, {"external_urls": {"spotify": "https://open.spotify.com/artist/51DevdOxIJin6DB1FXJpD1"}, "href": "https://api.spotify.com/v1/artists/51DevdOxIJin6DB1FXJpD1", "id": "51DevdOxIJin6DB1FXJpD1", "name": "UZI", "type": "artist", "uri": "spotify:artist:51DevdOxIJin6DB1FXJpD1"}, {"external_urls": {"spotify": "https://open.spotify.com/artist/0KOSzgkMlkeowt1tgIg6ca"}, "href": "https://api.spotify.com/v1/artists/0KOSzgkMlkeowt1tgIg6ca", "id": "0KOSzgkMlkeowt1tgIg6ca", "name": "Heijan", "type": "artist", "uri": "spotify:artist:0KOSzgkMlkeowt1tgIg6ca"}], "available_markets": ["AR", "AU", "AT", "BE", "BO", "BR", "BG", "CA", "CL", "CO", "CR", "CY", "CZ", "DK", "DO", "DE", "EC", "EE", "SV", "FI", "FR", "GR", "GT", "HN", "HK", "HU", "IS", "IE", "IT", "LV", "LT", "LU", "MY", "MT", "MX", "NL", "NZ", "NI", "NO", "PA", "PY", "PE", "PH", "PL", "PT", "SG", "SK", "ES", "SE", "CH", "TW", "TR", "UY", "US", "GB", "AD", "LI", "MC", "ID", "JP", "TH", "VN", "RO", "IL", "ZA", "SA", "AE", "BH", "QA", "OM", "KW", "EG", "MA", "DZ", "TN", "LB", "JO", "PS", "IN", "BY", "KZ", "MD", "UA", "AL", "BA", "HR", "ME", "MK", "RS", "SI", "KR", "BD", "PK", "LK", "GH", "KE", "NG", "TZ", "UG", "AG", "AM", "BS", "BB", "BZ", "BT", "BW", "BF", "CV", "CW", "DM", "FJ", "GM", "GE", "GD", "GW", "GY", "HT", "JM", "KI", "LS", "LR", "MW", "MV", "ML", "MH", "FM", "NA", "NR", "NE", "PW", "PG", "PR", "WS", "SM", "ST", "SN", "SC", "SL", "SB", "KN", "LC", "VC", "SR", "TL", "TO", "TT", "TV", "VU", "AZ", "BN", "BI", "KH", "CM", "TD", "KM", "GQ", "SZ", "GA", "GN", "KG", "LA", "MO", "MR", "MN", "NP", "RW", "TG", "UZ", "ZW", "BJ", "MG", "MU", "MZ", "AO", "CI", "DJ", "ZM", "CD", "CG", "IQ", "LY", "TJ", "VE", "ET", "XK"], "external_urls": {"spotify": "https://open.spotify.com/album/3PWIyRztWQE0AICzbD3Dpb"}, "href": "https://api.spotify.com/v1/albums/3PWIyRztWQE0AICzbD3Dpb", "id": "3PWIyRztWQE0AICzbD3Dpb", "images": [{"url": "https://i.scdn.co/image/ab67616d0000b273bde64a187cd5f52128634bce", "width": 640, "height": 640}, {"url": "https://i.scdn.co/image/ab67616d00001e02bde64a187cd5f52128634bce", "width": 300, "height": 300}, {"url": "https://i.scdn.co/image/ab67616d00004851bde64a187cd5f52128634bce", "width": 64, "height": 64}], "name": "HER YER FAVELA", "release_date": "2024-09-20", "release_date_precision": "day", "total_tracks": 1, "type": "album", "uri": "spotify:album:3PWIyRztWQE0AICzbD3Dpb"}, "artists": [{"external_urls": {"spotify": "https://open.spotify.com/artist/6dOAGo4z0syiCjbnlh4VSO"}, "href": "https://api.spotify.com/v1/artists/6dOAGo4z0syiCjbnlh4VSO", "id": "6dOAGo4z0syiCjbnlh4VSO", "name": "Critical", "type": "artist", "uri": "spotify:artist:6dOAGo4z0syiCjbnlh4VSO"}, {"external_urls": {"spotify": "https://open.spotify.com/artist/51DevdOxIJin6DB1FXJpD1"}, "href": "https://api.spotify.com/v1/artists/51DevdOxIJin6DB1FXJpD1", "id": "51DevdOxIJin6DB1FXJpD1", "name": "UZI", "type": "artist", "uri": "spotify:artist:51DevdOxIJin6DB1FXJpD1"}, {"external_urls": {"spotify": "https://open.spotify.com/artist/0KOSzgkMlkeowt1tgIg6ca"}, "href": "https://api.spotify.com/v1/artists/0KOSzgkMlkeowt1tgIg6ca", "id": "0KOSzgkMlkeowt1tgIg6ca", "name": "Heijan", "type": "artist", "uri": "spotify:artist:0KOSzgkMlkeowt1tgIg6ca"}, {"external_urls": {"spotify": "https://open.spotify.com/artist/3NPQ2qMGXAR0g1COJxuZ8r"}, "href": "https://api.spotify.com/v1/artists/3NPQ2qMGXAR0g1COJxuZ8r", "id": "3NPQ2qMGXAR0g1COJxuZ8r", "name": "Muti", "type": "artist", "uri": "spotify:artist:3NPQ2qMGXAR0g1COJxuZ8r"}], "available_markets": ["AR", "AU", "AT", "BE", "BO", "BR", "BG", "CA", "CL", "CO", "CR", "CY", "CZ", "DK", "DO", "DE", "EC", "EE", "SV", "FI", "FR", "GR", "GT", "HN", "HK", "HU", "IS", "IE", "IT", "LV", "LT", "LU", "MY", "MT", "MX", "NL", "NZ", "NI", "NO", "PA", "PY", "PE", "PH", "PL", "PT", "SG", "SK", "ES", "SE", "CH", "TW", "TR", "UY", "US", "GB", "AD", "LI", "MC", "ID", "JP", "TH", "VN", "RO", "IL", "ZA", "SA", "AE", "BH", "QA", "OM", "KW", "EG", "MA", "DZ", "TN", "LB", "JO", "PS", "IN", "BY", "KZ", "MD", "UA", "AL", "BA", "HR", "ME", "MK", "RS", "SI", "KR", "BD", "PK", "LK", "GH", "KE", "NG", "TZ", "UG", "AG", "AM", "BS", "BB", "BZ", "BT", "BW", "BF", "CV", "CW", "DM", "FJ", "GM", "GE", "GD", "GW", "GY", "HT", "JM", "KI", "LS", "LR", "MW", "MV", "ML", "MH", "FM", "NA", "NR", "NE", "PW", "PG", "PR", "WS", "SM", "ST", "SN", "SC", "SL", "SB", "KN", "LC", "VC", "SR", "TL", "TO", "TT", "TV", "VU", "AZ", "BN", "BI", "KH", "CM", "TD", "KM", "GQ", "SZ", "GA", "GN", "KG", "LA", "MO", "MR", "MN", "NP", "RW", "TG", "UZ", "ZW", "BJ", "MG", "MU", "MZ", "AO", "CI", "DJ", "ZM", "CD", "CG", "IQ", "LY", "TJ", "VE", "ET", "XK"], "disc_number": 1, "duration_ms": 213565, "explicit": true, "external_ids": {"isrc": "QZTPX2465726"}, "external_urls": {"spotify": "https://open.spotify.com/track/5fuPdS5jBncmRu9uu1MLOr"}, "href": "https://api.spotify.com/v1/tracks/5fuPdS5jBncmRu9uu1MLOr", "id": "5fuPdS5jBncmRu9uu1MLOr", "is_local": false, "name": "HER YER FAVELA", "popularity": 66, "preview_url": null, "track_number": 1, "type": "track", "uri": "spotify:track:5fuPdS5jBncmRu9uu1MLOr"}