{"album": {"album_type": "single", "artists": [{"external_urls": {"spotify": "https://open.spotify.com/artist/1wBzEp67t7GCnhi3iSYtnD"}, "href": "https://api.spotify.com/v1/artists/1wBzEp67t7GCnhi3iSYtnD", "id": "1wBzEp67t7GCnhi3iSYtnD", "name": "Snir Yamin", "type": "artist", "uri": "spotify:artist:1wBzEp67t7GCnhi3iSYtnD"}], "available_markets": [], "external_urls": {"spotify": "https://open.spotify.com/album/3VhXkkHhw3eeKXmt12koTN"}, "href": "https://api.spotify.com/v1/albums/3VhXkkHhw3eeKXmt12koTN", "id": "3VhXkkHhw3eeKXmt12koTN", "images": [{"url": "https://i.scdn.co/image/ab67616d0000b27322c4e9a8c7cd76b89c9bd770", "width": 640, "height": 640}, {"url": "https://i.scdn.co/image/ab67616d00001e0222c4e9a8c7cd76b89c9bd770", "width": 300, "height": 300}, {"url": "https://i.scdn.co/image/ab67616d0000485122c4e9a8c7cd76b89c9bd770", "width": 64, "height": 64}], "name": "Aftermath", "release_date": "2023-09-21", "release_date_precision": "day", "total_tracks": 1, "type": "album", "uri": "spotify:album:3VhXkkHhw3eeKXmt12koTN"}, "artists": [{"external_urls": {"spotify": "https://open.spotify.com/artist/1wBzEp67t7GCnhi3iSYtnD"}, "href": "https://api.spotify.com/v1/artists/1wBzEp67t7GCnhi3iSYtnD", "id": "1wBzEp67t7GCnhi3iSYtnD", "name": "Snir Yamin", "type": "artist", "uri": "spotify:artist:1wBzEp67t7GCnhi3iSYtnD"}], "available_markets": [], "disc_number": 1, "duration_ms": 215295, "explicit": false, "external_ids": {"isrc": "UKXN22332137"}, "external_urls": {"spotify": "https://open.spotify.com/track/75SyNc1SS0XDWhYnKI1g1i"}, "href": "https://api.spotify.com/v1/tracks/75SyNc1SS0XDWhYnKI1g1i", "id": "75SyNc1SS0XDWhYnKI1g1i", "is_local": false, "name": "Aftermath", "popularity": 0, "preview_url": null, "track_number": 1, "type": "track", "uri": "spotify:track:75SyNc1SS0XDWhYnKI1g1i"}