{"external_urls": {"spotify": "https://open.spotify.com/artist/0SfsnGyD8FpIN4U4WCkBZ5"}, "followers": {"href": null, "total": 4447940}, "genres": ["dutch house", "dutch trance", "edm", "pop dance", "progressive house", "trance"], "href": "https://api.spotify.com/v1/artists/0SfsnGyD8FpIN4U4WCkBZ5", "id": "0SfsnGyD8FpIN4U4WCkBZ5", "images": [{"url": "https://i.scdn.co/image/ab6761610000e5eb90db664ba1bf6574239f859d", "height": 640, "width": 640}, {"url": "https://i.scdn.co/image/ab6761610000517490db664ba1bf6574239f859d", "height": 320, "width": 320}, {"url": "https://i.scdn.co/image/ab6761610000f17890db664ba1bf6574239f859d", "height": 160, "width": 160}], "name": "Armin van Buuren", "popularity": 76, "type": "artist", "uri": "spotify:artist:0SfsnGyD8FpIN4U4WCkBZ5"}