{"external_urls": {"spotify": "https://open.spotify.com/artist/1IDBhlpDyKr53UKKxXRHXD"}, "followers": {"href": null, "total": 3421735}, "genres": ["dangdut koplo", "javanese dangdut", "lagu jawa"], "href": "https://api.spotify.com/v1/artists/1IDBhlpDyKr53UKKxXRHXD", "id": "1IDBhlpDyKr53UKKxXRHXD", "images": [{"url": "https://i.scdn.co/image/ab6761610000e5eb8398c5a4735d08bc7b23206c", "height": 640, "width": 640}, {"url": "https://i.scdn.co/image/ab676161000051748398c5a4735d08bc7b23206c", "height": 320, "width": 320}, {"url": "https://i.scdn.co/image/ab6761610000f1788398c5a4735d08bc7b23206c", "height": 160, "width": 160}], "name": "NDX A.K.A.", "popularity": 74, "type": "artist", "uri": "spotify:artist:1IDBhlpDyKr53UKKxXRHXD"}