{"external_urls": {"spotify": "https://open.spotify.com/artist/5cgPZA9muODieZY2hEkDN7"}, "followers": {"href": null, "total": 7234}, "genres": ["bulgarian folk", "women's choir"], "href": "https://api.spotify.com/v1/artists/5cgPZA9muODieZY2hEkDN7", "id": "5cgPZA9muODieZY2hEkDN7", "images": [{"url": "https://i.scdn.co/image/ab67616d0000b27307cd485068936851d44821fb", "height": 640, "width": 640}, {"url": "https://i.scdn.co/image/ab67616d00001e0207cd485068936851d44821fb", "height": 300, "width": 300}, {"url": "https://i.scdn.co/image/ab67616d0000485107cd485068936851d44821fb", "height": 64, "width": 64}], "name": "The Mystery Of The Bulgarian Voices", "popularity": 34, "type": "artist", "uri": "spotify:artist:5cgPZA9muODieZY2hEkDN7"}