{"external_urls": {"spotify": "https://open.spotify.com/artist/6mFYcrUtI8Hm3QrfuFIZUS"}, "followers": {"href": null, "total": 251081}, "genres": ["t-pop"], "href": "https://api.spotify.com/v1/artists/6mFYcrUtI8Hm3QrfuFIZUS", "id": "6mFYcrUtI8Hm3QrfuFIZUS", "images": [{"url": "https://i.scdn.co/image/ab6761610000e5eb35f3ef2a484ee27a9b552238", "height": 640, "width": 640}, {"url": "https://i.scdn.co/image/ab6761610000517435f3ef2a484ee27a9b552238", "height": 320, "width": 320}, {"url": "https://i.scdn.co/image/ab6761610000f17835f3ef2a484ee27a9b552238", "height": 160, "width": 160}], "name": "\u0e21\u0e19\u0e31\u0e2a\u0e27\u0e35\u0e23\u0e4c", "popularity": 53, "type": "artist", "uri": "spotify:artist:6mFYcrUtI8Hm3QrfuFIZUS"}