{"album": {"album_type": "single", "artists": [{"external_urls": {"spotify": "https://open.spotify.com/artist/1nX1HVIUo1Zfs3e2v3lFb9"}, "href": "https://api.spotify.com/v1/artists/1nX1HVIUo1Zfs3e2v3lFb9", "id": "1nX1HVIUo1Zfs3e2v3lFb9", "name": "Changg", "type": "artist", "uri": "spotify:artist:1nX1HVIUo1Zfs3e2v3lFb9"}, {"external_urls": {"spotify": "https://open.spotify.com/artist/5zT1Ku9mzzl6RW5y4z0hUK"}, "href": "https://api.spotify.com/v1/artists/5zT1Ku9mzzl6RW5y4z0hUK", "id": "5zT1Ku9mzzl6RW5y4z0hUK", "name": "Minh Huy", "type": "artist", "uri": "spotify:artist:5zT1Ku9mzzl6RW5y4z0hUK"}], "available_markets": ["AR", "AU", "AT", "BE", "BO", "BR", "BG", "CA", "CL", "CO", "CR", "CY", "CZ", "DK", "DO", "DE", "EC", "EE", "SV", "FI", "FR", "GR", "GT", "HN", "HK", "HU", "IS", "IE", "IT", "LV", "LT", "LU", "MY", "MT", "MX", "NL", "NZ", "NI", "NO", "PA", "PY", "PE", "PH", "PL", "PT", "SG", "SK", "ES", "SE", "CH", "TW", "TR", "UY", "US", "GB", "AD", "LI", "MC", "ID", "JP", "TH", "VN", "RO", "IL", "ZA", "SA", "AE", "BH", "QA", "OM", "KW", "EG", "MA", "DZ", "TN", "LB", "JO", "PS", "IN", "BY", "KZ", "MD", "UA", "AL", "BA", "HR", "ME", "MK", "RS", "SI", "KR", "BD", "PK", "LK", "GH", "KE", "NG", "TZ", "UG", "AG", "AM", "BS", "BB", "BZ", "BT", "BW", "BF", "CV", "CW", "DM", "FJ", "GM", "GE", "GD", "GW", "GY", "HT", "JM", "KI", "LS", "LR", "MW", "MV", "ML", "MH", "FM", "NA", "NR", "NE", "PW", "PG", "WS", "SM", "ST", "SN", "SC", "SL", "SB", "KN", "LC", "VC", "SR", "TL", "TO", "TT", "TV", "VU", "AZ", "BN", "BI", "KH", "CM", "TD", "KM", "GQ", "SZ", "GA", "GN", "KG", "LA", "MO", "MR", "MN", "NP", "RW", "TG", "UZ", "ZW", "BJ", "MG", "MU", "MZ", "AO", "CI", "DJ", "ZM", "CD", "CG", "IQ", "LY", "TJ", "VE", "ET", "XK"], "external_urls": {"spotify": "https://open.spotify.com/album/1TAJ1v7uOXi6lzXQSF3wjn"}, "href": "https://api.spotify.com/v1/albums/1TAJ1v7uOXi6lzXQSF3wjn", "id": "1TAJ1v7uOXi6lzXQSF3wjn", "images": [{"url": "https://i.scdn.co/image/ab67616d0000b2732882dbcd6195d4f0ef4b2cd4", "width": 640, "height": 640}, {"url": "https://i.scdn.co/image/ab67616d00001e022882dbcd6195d4f0ef4b2cd4", "width": 300, "height": 300}, {"url": "https://i.scdn.co/image/ab67616d000048512882dbcd6195d4f0ef4b2cd4", "width": 64, "height": 64}], "name": "Em Kh\u00f4ng Hi\u1ec3u", "release_date": "2021-06-28", "release_date_precision": "day", "total_tracks": 1, "type": "album", "uri": "spotify:album:1TAJ1v7uOXi6lzXQSF3wjn"}, "artists": [{"external_urls": {"spotify": "https://open.spotify.com/artist/1nX1HVIUo1Zfs3e2v3lFb9"}, "href": "https://api.spotify.com/v1/artists/1nX1HVIUo1Zfs3e2v3lFb9", "id": "1nX1HVIUo1Zfs3e2v3lFb9", "name": "Changg", "type": "artist", "uri": "spotify:artist:1nX1HVIUo1Zfs3e2v3lFb9"}, {"external_urls": {"spotify": "https://open.spotify.com/artist/5zT1Ku9mzzl6RW5y4z0hUK"}, "href": "https://api.spotify.com/v1/artists/5zT1Ku9mzzl6RW5y4z0hUK", "id": "5zT1Ku9mzzl6RW5y4z0hUK", "name": "Minh Huy", "type": "artist", "uri": "spotify:artist:5zT1Ku9mzzl6RW5y4z0hUK"}], "available_markets": ["AR", "AU", "AT", "BE", "BO", "BR", "BG", "CA", "CL", "CO", "CR", "CY", "CZ", "DK", "DO", "DE", "EC", "EE", "SV", "FI", "FR", "GR", "GT", "HN", "HK", "HU", "IS", "IE", "IT", "LV", "LT", "LU", "MY", "MT", "MX", "NL", "NZ", "NI", "NO", "PA", "PY", "PE", "PH", "PL", "PT", "SG", "SK", "ES", "SE", "CH", "TW", "TR", "UY", "US", "GB", "AD", "LI", "MC", "ID", "JP", "TH", "VN", "RO", "IL", "ZA", "SA", "AE", "BH", "QA", "OM", "KW", "EG", "MA", "DZ", "TN", "LB", "JO", "PS", "IN", "BY", "KZ", "MD", "UA", "AL", "BA", "HR", "ME", "MK", "RS", "SI", "KR", "BD", "PK", "LK", "GH", "KE", "NG", "TZ", "UG", "AG", "AM", "BS", "BB", "BZ", "BT", "BW", "BF", "CV", "CW", "DM", "FJ", "GM", "GE", "GD", "GW", "GY", "HT", "JM", "KI", "LS", "LR", "MW", "MV", "ML", "MH", "FM", "NA", "NR", "NE", "PW", "PG", "WS", "SM", "ST", "SN", "SC", "SL", "SB", "KN", "LC", "VC", "SR", "TL", "TO", "TT", "TV", "VU", "AZ", "BN", "BI", "KH", "CM", "TD", "KM", "GQ", "SZ", "GA", "GN", "KG", "LA", "MO", "MR", "MN", "NP", "RW", "TG", "UZ", "ZW", "BJ", "MG", "MU", "MZ", "AO", "CI", "DJ", "ZM", "CD", "CG", "IQ", "LY", "TJ", "VE", "ET", "XK"], "disc_number": 1, "duration_ms": 237419, "explicit": false, "external_ids": {"isrc": "SGUM72100270"}, "external_urls": {"spotify": "https://open.spotify.com/track/1izPmgSW7FV6XFdEOiTvOY"}, "href": "https://api.spotify.com/v1/tracks/1izPmgSW7FV6XFdEOiTvOY", "id": "1izPmgSW7FV6XFdEOiTvOY", "is_local": false, "name": "Em Kh\u00f4ng Hi\u1ec3u", "popularity": 57, "preview_url": null, "track_number": 1, "type": "track", "uri": "spotify:track:1izPmgSW7FV6XFdEOiTvOY"}