{"album": {"album_type": "single", "artists": [{"external_urls": {"spotify": "https://open.spotify.com/artist/2QZ60HlYJrsRqUACECzJ87"}, "href": "https://api.spotify.com/v1/artists/2QZ60HlYJrsRqUACECzJ87", "id": "2QZ60HlYJrsRqUACECzJ87", "name": "Johny Machette", "type": "artist", "uri": "spotify:artist:2QZ60HlYJrsRqUACECzJ87"}], "available_markets": ["AR", "AU", "AT", "BE", "BO", "BR", "BG", "CA", "CL", "CO", "CR", "CY", "CZ", "DK", "DO", "DE", "EC", "EE", "SV", "FI", "FR", "GR", "GT", "HN", "HK", "HU", "IS", "IE", "IT", "LV", "LT", "LU", "MY", "MT", "MX", "NL", "NZ", "NI", "NO", "PA", "PY", "PE", "PH", "PL", "PT", "SG", "SK", "ES", "SE", "CH", "TW", "TR", "UY", "US", "GB", "AD", "LI", "MC", "ID", "JP", "TH", "VN", "RO", "IL", "ZA", "SA", "AE", "BH", "QA", "OM", "KW", "EG", "MA", "DZ", "TN", "LB", "JO", "PS", "IN", "KZ", "MD", "UA", "AL", "BA", "HR", "ME", "MK", "RS", "SI", "KR", "BD", "PK", "LK", "GH", "KE", "NG", "TZ", "UG", "AG", "AM", "BS", "BB", "BZ", "BT", "BW", "BF", "CV", "CW", "DM", "FJ", "GM", "GE", "GD", "GW", "GY", "HT", "JM", "KI", "LS", "LR", "MW", "MV", "ML", "MH", "FM", "NA", "NR", "NE", "PW", "PG", "WS", "SM", "ST", "SN", "SC", "SL", "SB", "KN", "LC", "VC", "SR", "TL", "TO", "TT", "TV", "VU", "AZ", "BN", "BI", "KH", "CM", "TD", "KM", "GQ", "SZ", "GA", "GN", "KG", "LA", "MO", "MR", "MN", "NP", "RW", "TG", "UZ", "ZW", "BJ", "MG", "MU", "MZ", "AO", "CI", "DJ", "ZM", "CD", "CG", "IQ", "LY", "TJ", "VE", "ET", "XK"], "external_urls": {"spotify": "https://open.spotify.com/album/7LwJDJYDDYkcoyu7SuWjVp"}, "href": "https://api.spotify.com/v1/albums/7LwJDJYDDYkcoyu7SuWjVp", "id": "7LwJDJYDDYkcoyu7SuWjVp", "images": [{"url": "https://i.scdn.co/image/ab67616d0000b273c66ac990f93e8769773d17d7", "width": 640, "height": 640}, {"url": "https://i.scdn.co/image/ab67616d00001e02c66ac990f93e8769773d17d7", "width": 300, "height": 300}, {"url": "https://i.scdn.co/image/ab67616d00004851c66ac990f93e8769773d17d7", "width": 64, "height": 64}], "name": "V\u00e1no\u010dn\u00ed (feat. Teri Blitzen)", "release_date": "2022-04-24", "release_date_precision": "day", "total_tracks": 1, "type": "album", "uri": "spotify:album:7LwJDJYDDYkcoyu7SuWjVp"}, "artists": [{"external_urls": {"spotify": "https://open.spotify.com/artist/2QZ60HlYJrsRqUACECzJ87"}, "href": "https://api.spotify.com/v1/artists/2QZ60HlYJrsRqUACECzJ87", "id": "2QZ60HlYJrsRqUACECzJ87", "name": "Johny Machette", "type": "artist", "uri": "spotify:artist:2QZ60HlYJrsRqUACECzJ87"}, {"external_urls": {"spotify": "https://open.spotify.com/artist/4IkxApSUvBr5Uq9GnpIu88"}, "href": "https://api.spotify.com/v1/artists/4IkxApSUvBr5Uq9GnpIu88", "id": "4IkxApSUvBr5Uq9GnpIu88", "name": "Teri Blitzen", "type": "artist", "uri": "spotify:artist:4IkxApSUvBr5Uq9GnpIu88"}], "available_markets": ["AR", "AU", "AT", "BE", "BO", "BR", "BG", "CA", "CL", "CO", "CR", "CY", "CZ", "DK", "DO", "DE", "EC", "EE", "SV", "FI", "FR", "GR", "GT", "HN", "HK", "HU", "IS", "IE", "IT", "LV", "LT", "LU", "MY", "MT", "MX", "NL", "NZ", "NI", "NO", "PA", "PY", "PE", "PH", "PL", "PT", "SG", "SK", "ES", "SE", "CH", "TW", "TR", "UY", "US", "GB", "AD", "LI", "MC", "ID", "JP", "TH", "VN", "RO", "IL", "ZA", "SA", "AE", "BH", "QA", "OM", "KW", "EG", "MA", "DZ", "TN", "LB", "JO", "PS", "IN", "KZ", "MD", "UA", "AL", "BA", "HR", "ME", "MK", "RS", "SI", "KR", "BD", "PK", "LK", "GH", "KE", "NG", "TZ", "UG", "AG", "AM", "BS", "BB", "BZ", "BT", "BW", "BF", "CV", "CW", "DM", "FJ", "GM", "GE", "GD", "GW", "GY", "HT", "JM", "KI", "LS", "LR", "MW", "MV", "ML", "MH", "FM", "NA", "NR", "NE", "PW", "PG", "WS", "SM", "ST", "SN", "SC", "SL", "SB", "KN", "LC", "VC", "SR", "TL", "TO", "TT", "TV", "VU", "AZ", "BN", "BI", "KH", "CM", "TD", "KM", "GQ", "SZ", "GA", "GN", "KG", "LA", "MO", "MR", "MN", "NP", "RW", "TG", "UZ", "ZW", "BJ", "MG", "MU", "MZ", "AO", "CI", "DJ", "ZM", "CD", "CG", "IQ", "LY", "TJ", "VE", "ET", "XK"], "disc_number": 1, "duration_ms": 221054, "explicit": false, "external_ids": {"isrc": "CZL011500060"}, "external_urls": {"spotify": "https://open.spotify.com/track/2eDK36OyLEXUYP0DxlTLIE"}, "href": "https://api.spotify.com/v1/tracks/2eDK36OyLEXUYP0DxlTLIE", "id": "2eDK36OyLEXUYP0DxlTLIE", "is_local": false, "name": "V\u00e1no\u010dn\u00ed (feat. Teri Blitzen)", "popularity": 53, "preview_url": null, "track_number": 1, "type": "track", "uri": "spotify:track:2eDK36OyLEXUYP0DxlTLIE"}