{"album": {"album_type": "album", "artists": [{"external_urls": {"spotify": "https://open.spotify.com/artist/5CAruGjgds3QlF5ICtEnnc"}, "href": "https://api.spotify.com/v1/artists/5CAruGjgds3QlF5ICtEnnc", "id": "5CAruGjgds3QlF5ICtEnnc", "name": "Jairo Vera", "type": "artist", "uri": "spotify:artist:5CAruGjgds3QlF5ICtEnnc"}], "available_markets": ["AR", "AU", "AT", "BE", "BO", "BR", "BG", "CA", "CL", "CO", "CR", "CY", "CZ", "DK", "DO", "DE", "EC", "EE", "SV", "FI", "FR", "GR", "GT", "HN", "HK", "HU", "IS", "IE", "IT", "LV", "LT", "LU", "MY", "MT", "MX", "NL", "NZ", "NI", "NO", "PA", "PY", "PE", "PH", "PL", "PT", "SG", "SK", "ES", "SE", "CH", "TW", "TR", "UY", "US", "GB", "AD", "LI", "MC", "ID", "JP", "TH", "VN", "RO", "IL", "ZA", "SA", "AE", "BH", "QA", "OM", "KW", "EG", "MA", "DZ", "TN", "LB", "JO", "PS", "IN", "KZ", "MD", "UA", "AL", "BA", "HR", "ME", "MK", "RS", "SI", "KR", "BD", "PK", "LK", "GH", "KE", "NG", "TZ", "UG", "AG", "AM", "BS", "BB", "BZ", "BT", "BW", "BF", "CV", "CW", "DM", "FJ", "GM", "GE", "GD", "GW", "GY", "HT", "JM", "KI", "LS", "LR", "MW", "MV", "ML", "MH", "FM", "NA", "NR", "NE", "PW", "PG", "PR", "WS", "SM", "ST", "SN", "SC", "SL", "SB", "KN", "LC", "VC", "SR", "TL", "TO", "TT", "TV", "VU", "AZ", "BN", "BI", "KH", "CM", "TD", "KM", "GQ", "SZ", "GA", "GN", "KG", "LA", "MO", "MR", "MN", "NP", "RW", "TG", "UZ", "ZW", "BJ", "MG", "MU", "MZ", "AO", "CI", "DJ", "ZM", "CD", "CG", "IQ", "LY", "TJ", "VE", "ET", "XK"], "external_urls": {"spotify": "https://open.spotify.com/album/3VN2NF0LHVaNzSgWqXSlKi"}, "href": "https://api.spotify.com/v1/albums/3VN2NF0LHVaNzSgWqXSlKi", "id": "3VN2NF0LHVaNzSgWqXSlKi", "images": [{"url": "https://i.scdn.co/image/ab67616d0000b273b502bdf8b9b1ffc36b6774a2", "width": 640, "height": 640}, {"url": "https://i.scdn.co/image/ab67616d00001e02b502bdf8b9b1ffc36b6774a2", "width": 300, "height": 300}, {"url": "https://i.scdn.co/image/ab67616d00004851b502bdf8b9b1ffc36b6774a2", "width": 64, "height": 64}], "name": "De Vuelta A La Calle", "release_date": "2024-08-29", "release_date_precision": "day", "total_tracks": 14, "type": "album", "uri": "spotify:album:3VN2NF0LHVaNzSgWqXSlKi"}, "artists": [{"external_urls": {"spotify": "https://open.spotify.com/artist/5CAruGjgds3QlF5ICtEnnc"}, "href": "https://api.spotify.com/v1/artists/5CAruGjgds3QlF5ICtEnnc", "id": "5CAruGjgds3QlF5ICtEnnc", "name": "Jairo Vera", "type": "artist", "uri": "spotify:artist:5CAruGjgds3QlF5ICtEnnc"}, {"external_urls": {"spotify": "https://open.spotify.com/artist/3EiLUeyEcA6fbRPSHkG5kb"}, "href": "https://api.spotify.com/v1/artists/3EiLUeyEcA6fbRPSHkG5kb", "id": "3EiLUeyEcA6fbRPSHkG5kb", "name": "De La Ghetto", "type": "artist", "uri": "spotify:artist:3EiLUeyEcA6fbRPSHkG5kb"}], "available_markets": ["AR", "AU", "AT", "BE", "BO", "BR", "BG", "CA", "CL", "CO", "CR", "CY", "CZ", "DK", "DO", "DE", "EC", "EE", "SV", "FI", "FR", "GR", "GT", "HN", "HK", "HU", "IS", "IE", "IT", "LV", "LT", "LU", "MY", "MT", "MX", "NL", "NZ", "NI", "NO", "PA", "PY", "PE", "PH", "PL", "PT", "SG", "SK", "ES", "SE", "CH", "TW", "TR", "UY", "US", "GB", "AD", "LI", "MC", "ID", "JP", "TH", "VN", "RO", "IL", "ZA", "SA", "AE", "BH", "QA", "OM", "KW", "EG", "MA", "DZ", "TN", "LB", "JO", "PS", "IN", "KZ", "MD", "UA", "AL", "BA", "HR", "ME", "MK", "RS", "SI", "KR", "BD", "PK", "LK", "GH", "KE", "NG", "TZ", "UG", "AG", "AM", "BS", "BB", "BZ", "BT", "BW", "BF", "CV", "CW", "DM", "FJ", "GM", "GE", "GD", "GW", "GY", "HT", "JM", "KI", "LS", "LR", "MW", "MV", "ML", "MH", "FM", "NA", "NR", "NE", "PW", "PG", "PR", "WS", "SM", "ST", "SN", "SC", "SL", "SB", "KN", "LC", "VC", "SR", "TL", "TO", "TT", "TV", "VU", "AZ", "BN", "BI", "KH", "CM", "TD", "KM", "GQ", "SZ", "GA", "GN", "KG", "LA", "MO", "MR", "MN", "NP", "RW", "TG", "UZ", "ZW", "BJ", "MG", "MU", "MZ", "AO", "CI", "DJ", "ZM", "CD", "CG", "IQ", "LY", "TJ", "VE", "ET", "XK"], "disc_number": 1, "duration_ms": 179086, "explicit": true, "external_ids": {"isrc": "CLEM42101018"}, "external_urls": {"spotify": "https://open.spotify.com/track/2gBLsoctq0gJn3dr3gl83x"}, "href": "https://api.spotify.com/v1/tracks/2gBLsoctq0gJn3dr3gl83x", "id": "2gBLsoctq0gJn3dr3gl83x", "is_local": false, "name": "Choka", "popularity": 63, "preview_url": null, "track_number": 14, "type": "track", "uri": "spotify:track:2gBLsoctq0gJn3dr3gl83x"}