{"album": {"album_type": "album", "artists": [{"external_urls": {"spotify": "https://open.spotify.com/artist/3fA5zBQWEa0uzYo43SvXaj"}, "href": "https://api.spotify.com/v1/artists/3fA5zBQWEa0uzYo43SvXaj", "id": "3fA5zBQWEa0uzYo43SvXaj", "name": "Peter J\u00f6back", "type": "artist", "uri": "spotify:artist:3fA5zBQWEa0uzYo43SvXaj"}], "available_markets": ["AR", "AU", "AT", "BE", "BO", "BR", "BG", "CA", "CL", "CO", "CR", "CY", "CZ", "DK", "DO", "DE", "EC", "EE", "SV", "FI", "FR", "GR", "GT", "HN", "HK", "HU", "IS", "IE", "IT", "LV", "LT", "LU", "MY", "MT", "MX", "NL", "NZ", "NI", "NO", "PA", "PY", "PE", "PH", "PL", "PT", "SG", "SK", "ES", "SE", "CH", "TW", "TR", "UY", "US", "GB", "AD", "LI", "MC", "ID", "JP", "TH", "VN", "RO", "IL", "ZA", "SA", "AE", "BH", "QA", "OM", "KW", "EG", "MA", "DZ", "TN", "LB", "JO", "PS", "IN", "BY", "KZ", "MD", "UA", "AL", "BA", "HR", "ME", "MK", "RS", "SI", "KR", "BD", "PK", "LK", "GH", "KE", "NG", "TZ", "UG", "AG", "AM", "BS", "BB", "BZ", "BT", "BW", "BF", "CV", "CW", "DM", "FJ", "GM", "GE", "GD", "GW", "GY", "HT", "JM", "KI", "LS", "LR", "MW", "MV", "ML", "MH", "FM", "NA", "NR", "NE", "PW", "PG", "PR", "WS", "SM", "ST", "SN", "SC", "SL", "SB", "KN", "LC", "VC", "SR", "TL", "TO", "TT", "TV", "VU", "AZ", "BN", "BI", "KH", "CM", "TD", "KM", "GQ", "SZ", "GA", "GN", "KG", "LA", "MO", "MR", "MN", "NP", "RW", "TG", "UZ", "ZW", "BJ", "MG", "MU", "MZ", "AO", "CI", "DJ", "ZM", "CD", "CG", "IQ", "LY", "TJ", "VE", "ET", "XK"], "external_urls": {"spotify": "https://open.spotify.com/album/7CKtVeB9uIO6clD9N7qCLl"}, "href": "https://api.spotify.com/v1/albums/7CKtVeB9uIO6clD9N7qCLl", "id": "7CKtVeB9uIO6clD9N7qCLl", "images": [{"url": "https://i.scdn.co/image/ab67616d0000b2738e5cd147ee2e068f8de98d08", "width": 640, "height": 640}, {"url": "https://i.scdn.co/image/ab67616d00001e028e5cd147ee2e068f8de98d08", "width": 300, "height": 300}, {"url": "https://i.scdn.co/image/ab67616d000048518e5cd147ee2e068f8de98d08", "width": 64, "height": 64}], "name": "Jag kommer hem igen till jul", "release_date": "2019-11-08", "release_date_precision": "day", "total_tracks": 19, "type": "album", "uri": "spotify:album:7CKtVeB9uIO6clD9N7qCLl"}, "artists": [{"external_urls": {"spotify": "https://open.spotify.com/artist/3fA5zBQWEa0uzYo43SvXaj"}, "href": "https://api.spotify.com/v1/artists/3fA5zBQWEa0uzYo43SvXaj", "id": "3fA5zBQWEa0uzYo43SvXaj", "name": "Peter J\u00f6back", "type": "artist", "uri": "spotify:artist:3fA5zBQWEa0uzYo43SvXaj"}], "available_markets": ["AR", "AU", "AT", "BE", "BO", "BR", "BG", "CA", "CL", "CO", "CR", "CY", "CZ", "DK", "DO", "DE", "EC", "EE", "SV", "FI", "FR", "GR", "GT", "HN", "HK", "HU", "IS", "IE", "IT", "LV", "LT", "LU", "MY", "MT", "MX", "NL", "NZ", "NI", "NO", "PA", "PY", "PE", "PH", "PL", "PT", "SG", "SK", "ES", "SE", "CH", "TW", "TR", "UY", "US", "GB", "AD", "LI", "MC", "ID", "JP", "TH", "VN", "RO", "IL", "ZA", "SA", "AE", "BH", "QA", "OM", "KW", "EG", "MA", "DZ", "TN", "LB", "JO", "PS", "IN", "BY", "KZ", "MD", "UA", "AL", "BA", "HR", "ME", "MK", "RS", "SI", "KR", "BD", "PK", "LK", "GH", "KE", "NG", "TZ", "UG", "AG", "AM", "BS", "BB", "BZ", "BT", "BW", "BF", "CV", "CW", "DM", "FJ", "GM", "GE", "GD", "GW", "GY", "HT", "JM", "KI", "LS", "LR", "MW", "MV", "ML", "MH", "FM", "NA", "NR", "NE", "PW", "PG", "PR", "WS", "SM", "ST", "SN", "SC", "SL", "SB", "KN", "LC", "VC", "SR", "TL", "TO", "TT", "TV", "VU", "AZ", "BN", "BI", "KH", "CM", "TD", "KM", "GQ", "SZ", "GA", "GN", "KG", "LA", "MO", "MR", "MN", "NP", "RW", "TG", "UZ", "ZW", "BJ", "MG", "MU", "MZ", "AO", "CI", "DJ", "ZM", "CD", "CG", "IQ", "LY", "TJ", "VE", "ET", "XK"], "disc_number": 1, "duration_ms": 230280, "explicit": false, "external_ids": {"isrc": "SEBGA0207130"}, "external_urls": {"spotify": "https://open.spotify.com/track/3eusN83SiYVrSA3hG4drFy"}, "href": "https://api.spotify.com/v1/tracks/3eusN83SiYVrSA3hG4drFy", "id": "3eusN83SiYVrSA3hG4drFy", "is_local": false, "name": "Jag kommer hem igen till jul", "popularity": 59, "preview_url": null, "track_number": 4, "type": "track", "uri": "spotify:track:3eusN83SiYVrSA3hG4drFy"}