{"album": {"album_type": "album", "artists": [{"external_urls": {"spotify": "https://open.spotify.com/artist/40YXr3tdSqFv0kfmgjj8vP"}, "href": "https://api.spotify.com/v1/artists/40YXr3tdSqFv0kfmgjj8vP", "id": "40YXr3tdSqFv0kfmgjj8vP", "name": "ANNA ASTI", "type": "artist", "uri": "spotify:artist:40YXr3tdSqFv0kfmgjj8vP"}], "available_markets": [], "external_urls": {"spotify": "https://open.spotify.com/album/1RMfMLNhXhXPZjJaaiHtuu"}, "href": "https://api.spotify.com/v1/albums/1RMfMLNhXhXPZjJaaiHtuu", "id": "1RMfMLNhXhXPZjJaaiHtuu", "images": [{"url": "https://i.scdn.co/image/ab67616d0000b27394bb7eb0a0acbbe54b1d7048", "width": 640, "height": 640}, {"url": "https://i.scdn.co/image/ab67616d00001e0294bb7eb0a0acbbe54b1d7048", "width": 300, "height": 300}, {"url": "https://i.scdn.co/image/ab67616d0000485194bb7eb0a0acbbe54b1d7048", "width": 64, "height": 64}], "name": "\u0424\u0435\u043d\u0438\u043a\u0441", "release_date": "2022-06-24", "release_date_precision": "day", "total_tracks": 11, "type": "album", "uri": "spotify:album:1RMfMLNhXhXPZjJaaiHtuu"}, "artists": [{"external_urls": {"spotify": "https://open.spotify.com/artist/40YXr3tdSqFv0kfmgjj8vP"}, "href": "https://api.spotify.com/v1/artists/40YXr3tdSqFv0kfmgjj8vP", "id": "40YXr3tdSqFv0kfmgjj8vP", "name": "ANNA ASTI", "type": "artist", "uri": "spotify:artist:40YXr3tdSqFv0kfmgjj8vP"}], "available_markets": [], "disc_number": 1, "duration_ms": 237837, "explicit": false, "external_ids": {"isrc": "RUA1D2242027"}, "external_urls": {"spotify": "https://open.spotify.com/track/4zOLAk87gHl97sbqmntbJG"}, "href": "https://api.spotify.com/v1/tracks/4zOLAk87gHl97sbqmntbJG", "id": "4zOLAk87gHl97sbqmntbJG", "is_local": false, "name": "\u041f\u043e \u0431\u0430\u0440\u0430\u043c", "popularity": 23, "preview_url": null, "track_number": 4, "type": "track", "uri": "spotify:track:4zOLAk87gHl97sbqmntbJG"}