{"album": {"album_type": "album", "artists": [{"external_urls": {"spotify": "https://open.spotify.com/artist/0b62itBWBdLgiecXjXCqKC"}, "href": "https://api.spotify.com/v1/artists/0b62itBWBdLgiecXjXCqKC", "id": "0b62itBWBdLgiecXjXCqKC", "name": "Maxwell", "type": "artist", "uri": "spotify:artist:0b62itBWBdLgiecXjXCqKC"}], "available_markets": ["AR", "AU", "AT", "BE", "BO", "BR", "BG", "CA", "CL", "CO", "CR", "CY", "CZ", "DK", "DO", "DE", "EC", "EE", "SV", "FI", "FR", "GR", "GT", "HN", "HK", "HU", "IS", "IE", "IT", "LV", "LT", "LU", "MY", "MT", "MX", "NL", "NZ", "NI", "NO", "PA", "PY", "PE", "PH", "PL", "PT", "SG", "SK", "ES", "SE", "CH", "TW", "TR", "UY", "US", "GB", "AD", "LI", "MC", "ID", "JP", "TH", "VN", "RO", "IL", "ZA", "SA", "AE", "BH", "QA", "OM", "KW", "EG", "MA", "DZ", "TN", "LB", "JO", "PS", "IN", "KZ", "MD", "UA", "AL", "BA", "HR", "ME", "MK", "RS", "SI", "KR", "BD", "PK", "LK", "GH", "KE", "NG", "TZ", "UG", "AG", "AM", "BS", "BB", "BZ", "BT", "BW", "BF", "CV", "CW", "DM", "FJ", "GM", "GE", "GD", "GW", "GY", "HT", "JM", "KI", "LS", "LR", "MW", "MV", "ML", "MH", "FM", "NA", "NR", "NE", "PW", "PG", "WS", "SM", "ST", "SN", "SC", "SL", "SB", "KN", "LC", "VC", "SR", "TL", "TO", "TT", "TV", "VU", "AZ", "BN", "BI", "KH", "CM", "TD", "KM", "GQ", "SZ", "GA", "GN", "KG", "LA", "MO", "MR", "MN", "NP", "RW", "TG", "UZ", "ZW", "BJ", "MG", "MU", "MZ", "AO", "CI", "DJ", "ZM", "CD", "CG", "IQ", "LY", "TJ", "VE", "ET", "XK"], "external_urls": {"spotify": "https://open.spotify.com/album/4Y17P7EwESVpNc1qR8ZQJl"}, "href": "https://api.spotify.com/v1/albums/4Y17P7EwESVpNc1qR8ZQJl", "id": "4Y17P7EwESVpNc1qR8ZQJl", "images": [{"url": "https://i.scdn.co/image/ab67616d0000b2735291d5399a33f2351eeaa4f8", "width": 640, "height": 640}, {"url": "https://i.scdn.co/image/ab67616d00001e025291d5399a33f2351eeaa4f8", "width": 300, "height": 300}, {"url": "https://i.scdn.co/image/ab67616d000048515291d5399a33f2351eeaa4f8", "width": 64, "height": 64}], "name": "Safari", "release_date": "2016-12-16", "release_date_precision": "day", "total_tracks": 10, "type": "album", "uri": "spotify:album:4Y17P7EwESVpNc1qR8ZQJl"}, "artists": [{"external_urls": {"spotify": "https://open.spotify.com/artist/0b62itBWBdLgiecXjXCqKC"}, "href": "https://api.spotify.com/v1/artists/0b62itBWBdLgiecXjXCqKC", "id": "0b62itBWBdLgiecXjXCqKC", "name": "Maxwell", "type": "artist", "uri": "spotify:artist:0b62itBWBdLgiecXjXCqKC"}, {"external_urls": {"spotify": "https://open.spotify.com/artist/0Dvx6p8JDyzeOPGmaCIH1L"}, "href": "https://api.spotify.com/v1/artists/0Dvx6p8JDyzeOPGmaCIH1L", "id": "0Dvx6p8JDyzeOPGmaCIH1L", "name": "RAF Camora", "type": "artist", "uri": "spotify:artist:0Dvx6p8JDyzeOPGmaCIH1L"}, {"external_urls": {"spotify": "https://open.spotify.com/artist/1aS5tqEs9ci5P9KD9tZWa6"}, "href": "https://api.spotify.com/v1/artists/1aS5tqEs9ci5P9KD9tZWa6", "id": "1aS5tqEs9ci5P9KD9tZWa6", "name": "Bonez MC", "type": "artist", "uri": "spotify:artist:1aS5tqEs9ci5P9KD9tZWa6"}], "available_markets": ["AR", "AU", "AT", "BE", "BO", "BR", "BG", "CA", "CL", "CO", "CR", "CY", "CZ", "DK", "DO", "DE", "EC", "EE", "SV", "FI", "FR", "GR", "GT", "HN", "HK", "HU", "IS", "IE", "IT", "LV", "LT", "LU", "MY", "MT", "MX", "NL", "NZ", "NI", "NO", "PA", "PY", "PE", "PH", "PL", "PT", "SG", "SK", "ES", "SE", "CH", "TW", "TR", "UY", "US", "GB", "AD", "LI", "MC", "ID", "JP", "TH", "VN", "RO", "IL", "ZA", "SA", "AE", "BH", "QA", "OM", "KW", "EG", "MA", "DZ", "TN", "LB", "JO", "PS", "IN", "KZ", "MD", "UA", "AL", "BA", "HR", "ME", "MK", "RS", "SI", "KR", "BD", "PK", "LK", "GH", "KE", "NG", "TZ", "UG", "AG", "AM", "BS", "BB", "BZ", "BT", "BW", "BF", "CV", "CW", "DM", "FJ", "GM", "GE", "GD", "GW", "GY", "HT", "JM", "KI", "LS", "LR", "MW", "MV", "ML", "MH", "FM", "NA", "NR", "NE", "PW", "PG", "WS", "SM", "ST", "SN", "SC", "SL", "SB", "KN", "LC", "VC", "SR", "TL", "TO", "TT", "TV", "VU", "AZ", "BN", "BI", "KH", "CM", "TD", "KM", "GQ", "SZ", "GA", "GN", "KG", "LA", "MO", "MR", "MN", "NP", "RW", "TG", "UZ", "ZW", "BJ", "MG", "MU", "MZ", "AO", "CI", "DJ", "ZM", "CD", "CG", "IQ", "LY", "TJ", "VE", "ET", "XK"], "disc_number": 1, "duration_ms": 158968, "explicit": true, "external_ids": {"isrc": "DETX91500458"}, "external_urls": {"spotify": "https://open.spotify.com/track/6hjck7ERXicpsW51UkdHCA"}, "href": "https://api.spotify.com/v1/tracks/6hjck7ERXicpsW51UkdHCA", "id": "6hjck7ERXicpsW51UkdHCA", "is_local": false, "name": "Safari", "popularity": 60, "preview_url": null, "track_number": 2, "type": "track", "uri": "spotify:track:6hjck7ERXicpsW51UkdHCA"}